Workbook
Name _Div1: #REF!
Name _Div1: #REF!
Name _Div2: #REF!
Name _Div2: #REF!
Name _Div3: #REF!
Name _Div3: #REF!
Name _Div4: #REF!
Name _Div4: #REF!
Name _Regression_Int: 1
Name coup: [1]Convexity!$C$7
Name g_firm: #REF!
Name g_firm: #REF!
Name g_firm: #REF!
Name IQ_CH: 110000
Name IQ_CQ: 5000
Name IQ_CY: 10000
Name IQ_DAILY: 500000
Name IQ_FH: 100000
Name IQ_FQ: 500
Name IQ_FY: 1000
Name IQ_LTM: 2000
Name IQ_MONTH: 15000
Name IQ_NTM: 6000
Name IQ_WEEK: 50000
Name IQ_YTD: 3000
Name k: #REF!
Name k: #REF!
Name k: #REF!
Name k_eq: #REF!
Name k_eq: #REF!
Name mat: [1]Convexity!$C$9
Name price: [1]Convexity!$C$10
Name Price4: #REF!
Name Price4: #REF!
Name Price4: #REF!
Name Print_Area_MI: #REF!
Name Print_Area_MI: #REF!
Name rdebt: #REF!
Name rdebt: #REF!
Name Selling_Price: '[2]Base Case'!$B$11
Name tax_rate: #REF!
Name tax_rate: #REF!
Name tax_rate: #REF!
Name taxtable: #REF!
Name taxtable: #REF!
Name taxtable: #REF!
Name taxtable: #REF!
Name taxtable: #REF!
Name term_g: #REF!
Name term_g: #REF!
Name Variable_Cost_per_unit: '[2]Base Case'!$B$12
Name WACC_5: #REF!
Name WACC_5: #REF!
Name WACC_5: #REF!
Name ytm: [1]Convexity!$C$8

Sheet Capital Allocation
B2: Capital Allocation. Optimal Captial Allocation using Maixum Utility
B3: Capital Allocation > Asset Classes Allocation > Security Selection
B5: Risky Pf (P) only
B6: rf: rate of return of risk-free asset | D6: ='Data. Securities'!E7 -> 0.04246
B7: E(Rp): expected return of risky pf | D7: ='Asset Classes Allocation'!D26 -> 0.1833731
B8: 𝜎 p: SD of risky pf | D8: ='Asset Classes Allocation'!E26 -> 0.19104045
B10: Complete Pf (C). Risk free + Risky Pf
B11: y: weight of risky pf | D11: =(D7-D6)/(D17*D8^2) -> 0.52175782
B12: 1-y: weight of risk free asset | D12: =1-D11 -> 0.47824218
B13: E(rc): expected return of the Complete pf | D13: =D11*D7+D12*D6 -> 0.11598251
B14: 𝜎 c: SD of Complete pf | D14: =D11*D8 -> 0.099676851
B15: Slope: Capital Allocation Line ( Sharpe) | D15: =(D7-D6)/D8 -> 0.73760869
B16: Risk Tolerance Score | D16: 63
B17: Risk Aversion Index (A: 1~20)* | D17: =20*(1-D16/100) -> 7.4
B18: Utility at the risk aversion level | D18: =D13-1/2*D17*D14^2 -> 0.079221256
B19: *Bear (1~5), Normal (1~10), Bull (1~20), Bubble (1~30)
F21: 0.079221256
B22: W of risky pf: y | C22: E(rc) on CAL | D22: 𝜎 c | E22: Utiliity | F22: E(rc) on Indiff.
B23: Max. U | C23: =D13 -> 0.11598251 | D23: =D14 -> 0.099676851 | E23: =D18 -> 0.079221256 | F23: =$F$21+1/2*$D$17*D23^2 -> 0.11598251
B24: 0.1 | C24: 0.05655131 | D24: 0.019104045 | E24: 0.055200941 | F24: =$F$21+1/2*$D$17*D24^2 -> 0.080571625
B25: 0.2 | C25: 0.07064262 | D25: 0.038208091 | E25: 0.065241145 | F25: =$F$21+1/2*$D$17*D25^2 -> 0.084622731
B26: 0.3 | C26: 0.08473393 | D26: 0.057312136 | E26: 0.07258061 | F26: =$F$21+1/2*$D$17*D26^2 -> 0.091374575
B27: 0.4 | C27: 0.09882524 | D27: 0.076416182 | E27: 0.077219339 | F27: =$F$21+1/2*$D$17*D27^2 -> 0.10082716
B28: 0.5 | C28: 0.11291655 | D28: 0.095520227 | E28: 0.079157329 | F28: =$F$21+1/2*$D$17*D28^2 -> 0.11298048
B29: 0.6 | C29: 0.12700786 | D29: 0.11462427 | E29: 0.078394582 | F29: =$F$21+1/2*$D$17*D29^2 -> 0.12783453
B30: 0.7 | C30: 0.14109917 | D30: 0.13372832 | E30: 0.074931097 | F30: =$F$21+1/2*$D$17*D30^2 -> 0.14538933
B31: 0.8 | C31: 0.15519048 | D31: 0.15283236 | E31: 0.068766874 | F31: =$F$21+1/2*$D$17*D31^2 -> 0.16564486
B32: 0.9 | C32: 0.16928179 | D32: 0.17193641 | E32: 0.059901914 | F32: =$F$21+1/2*$D$17*D32^2 -> 0.18860113
B33: 1 | C33: 0.1833731 | D33: 0.19104045 | E33: 0.048336216 | F33: =$F$21+1/2*$D$17*D33^2 -> 0.21425814

Sheet Asset Classes Allocation
B2: Asset Classes Allocation Analysis: Optimal Complete Pf Model
B3: Capital Allocation > Asset Classes Allocation > Security Selection
B5: Securities | C5: Expected Return | D5: Standard Deviation | E5: Corr. Coefficient B,E | F5: Covariance B,E | H5: Efficient Frontier meets CAL with Optimal Risky Pf
B6: Bond Pf (B) | C6: ='Data. Bond Duration & Convexity'!C16 -> 0.0260605 | D6: ='Data. Securities'!O8 -> 0.028165402 | E6: =CORREL('Data. Securities'!AU57:AU176,'Data. Securities'!AX57:AX176) -> 0.47856013 | F6: =$D$6*$D$7*$E$6 -> 0.0025750034
B7: Equity Pf (E) | C7: ='Security Allocation'!C65+C8 -> 0.1833731 | D7: ='Security Allocation'!C66 -> 0.19104045
B8: T-Bill | C8: 0.04246 | D8: 0
B10: Risky Asset Portfolio: Weights | F10: Reward to Variability
B11: Bond weight | C11: Equity weight | D11: Expected Return | E11: Standard Deviation | F11: (Sharpe ratio)
B12: 1 | C12: 0 | D12: =$C$6*$B12+$C$7*$C12 -> 0.0260605 | E12: =($B12^2*$D$6^2+$C12^2*$D$7^2+2*$B12*$C12*$F$6)^0.5 -> 0.028165402 | F12: =(D12-$C$8)/E12 -> -0.58225691
B13: 0.9 | C13: 0.1 | D13: =$C$6*$B13+$C$7*$C13 -> 0.04179176 | E13: =($B13^2*$D$6^2+$C13^2*$D$7^2+2*$B13*$C13*$F$6)^0.5 -> 0.038354009 | F13: =(D13-$C$8)/E13 -> -0.017422951
B14: 0.8 | C14: 0.2 | D14: =$C$6*$B14+$C$7*$C14 -> 0.05752302 | E14: =($B14^2*$D$6^2+$C14^2*$D$7^2+2*$B14*$C14*$F$6)^0.5 -> 0.052835261 | F14: =(D14-$C$8)/E14 -> 0.28509408
B15: 0.7 | C15: 0.3 | D15: =$C$6*$B15+$C$7*$C15 -> 0.07325428 | E15: =($B15^2*$D$6^2+$C15^2*$D$7^2+2*$B15*$C15*$F$6)^0.5 -> 0.068955743 | F15: =(D15-$C$8)/E15 -> 0.44658035
B16: 0.6 | C16: 0.4 | D16: =$C$6*$B16+$C$7*$C16 -> 0.08898554 | E16: =($B16^2*$D$6^2+$C16^2*$D$7^2+2*$B16*$C16*$F$6)^0.5 -> 0.08579638 | F16: =(D16-$C$8)/E16 -> 0.54227859
B17: 0.5 | C17: 0.5 | D17: =$C$6*$B17+$C$7*$C17 -> 0.1047168 | E17: =($B17^2*$D$6^2+$C17^2*$D$7^2+2*$B17*$C17*$F$6)^0.5 -> 0.10300455 | F17: =(D17-$C$8)/E17 -> 0.60440823
B18: 0.4 | C18: 0.6 | D18: =$C$6*$B18+$C$7*$C18 -> 0.12044806 | E18: =($B18^2*$D$6^2+$C18^2*$D$7^2+2*$B18*$C18*$F$6)^0.5 -> 0.1204228 | F18: =(D18-$C$8)/E18 -> 0.6476187
B19: 0.3 | C19: 0.7 | D19: =$C$6*$B19+$C$7*$C19 -> 0.13617932 | E19: =($B19^2*$D$6^2+$C19^2*$D$7^2+2*$B19*$C19*$F$6)^0.5 -> 0.13797159 | F19: =(D19-$C$8)/E19 -> 0.67926533
B20: 0.2 | C20: 0.8 | D20: =$C$6*$B20+$C$7*$C20 -> 0.15191058 | E20: =($B20^2*$D$6^2+$C20^2*$D$7^2+2*$B20*$C20*$F$6)^0.5 -> 0.15560676 | F20: =(D20-$C$8)/E20 -> 0.70337934
B21: 0.1 | C21: 0.9 | D21: =$C$6*$B21+$C$7*$C21 -> 0.16764184 | E21: =($B21^2*$D$6^2+$C21^2*$D$7^2+2*$B21*$C21*$F$6)^0.5 -> 0.17330194 | F21: =(D21-$C$8)/E21 -> 0.72233375
B22: 0 | C22: 1 | D22: =$C$6*$B22+$C$7*$C22 -> 0.1833731 | E22: =($B22^2*$D$6^2+$C22^2*$D$7^2+2*$B22*$C22*$F$6)^0.5 -> 0.19104045 | F22: =(D22-$C$8)/E22 -> 0.73760869
B23: A. Minimum Variance Portfolio of Risky Assets | D23: Expected Return | E23: Min. Standard Deviation | F23: Sharpe Ratio
B24: 1 | C24: =1-$B$24 -> 0 | D24: =$C$6*$B24+$C$7*$C24 -> 0.0260605 | E24: =((($B$24^2)*($D$6^2))+(($C$24^2)*($D$7^2))+(2*$B$24*$C$24*$F$6))^0.5 -> 0.028165402 | F24: =(D24-$C$8)/E24 -> -0.58225691 | G24: short-not allowed
B25: B. Optimal Risky Portfolio. Maximum of Sharpe ratio | D25: Expected Return | E25: Standard Deviation | F25: Max. of Sharpe Ratio
B26: 0 | C26: =1-B26 -> 1 | D26: =$C$6*$B26+$C$7*$C26 -> 0.1833731 | E26: =((($B$26^2)*($D$6^2))+(($C$26^2)*($D$7^2))+(2*$B$26*$C$26*$F$6))^0.5 -> 0.19104045 | F26: =(D26-$C$8)/E26 -> 0.73760869 | G26: short-not allowed
B28: C. Optimal Complete Portfolio with U w/ Risk-Free Asset
B29: Weight y: Optimal Risky Portfolio | D29: =(D26-C8)/('Capital Allocation'!D17*'Asset Classes Allocation'!E26^2) -> 0.52175782
B30: Weight (1-y): Risk-Free Asset | D30: =1-D29 -> 0.47824218
B31: Bond weight in the Optimal Complete Pf | D31: =D29*B26 -> 0
B32: Equity weight in the Optimal Complete Pf | D32: =D29*C26 -> 0.52175782
B33: E(rc): expected return of the Overall Complete pf | D33: =D29*D26+D30*C8 -> 0.11598251
B34: 𝜎 c: SD of Overall Complete pf | D34: =D29*E26 -> 0.099676851
B35: Sharpe Ratio (Max. Slope of CAL) | D35: =(D33-C8)/D34 -> 0.73760869

Sheet Security Allocation
B2: Index Portfolio Model. SPDR + Active Portfolio (Large Growth)
B4: Panel A. Risk Parameters of Pf A (annualized) | C4: ='Data. Securities'!F6 -> IYC | D4: ='Data. Securities'!G6 -> AMZN | E4: ='Data. Securities'!H6 -> TSLA | F4: ='Data. Securities'!I6 -> COST | G4: ='Data. Securities'!J6 -> NFLX | H4: ='Data. Securities'!K6 -> BKNG | I4: ='Data. Securities'!L6 -> HD | J4: ='Data. Securities'!M6 -> SBUX | K4: ='Data. Securities'!N6 -> WMT
B5: Beta | C5: ='Data. Securities'!F17 -> 1 | D5: ='Data. Securities'!G17 -> 1.1614255 | E5: ='Data. Securities'!H17 -> 1.7858873 | F5: ='Data. Securities'!I17 -> 0.73994352 | G5: ='Data. Securities'!J17 -> 1.1486187 | H5: ='Data. Securities'!K17 -> 1.0050217 | I5: ='Data. Securities'!L17 -> 0.85338102 | J5: ='Data. Securities'!M17 -> 0.73534517 | K5: ='Data. Securities'!N17 -> 0.46119564
B6: SD of Excess Return | C6: ='Data. Securities'!F8 -> 0.18920755 | D6: ='Data. Securities'!G8 -> 0.31095122 | E6: ='Data. Securities'!H8 -> 0.63117784 | F6: ='Data. Securities'!I8 -> 0.20993206 | G6: ='Data. Securities'!J8 -> 0.41059796 | H6: ='Data. Securities'!K8 -> 0.29486101 | I6: ='Data. Securities'!L8 -> 0.22083305 | J6: ='Data. Securities'!M8 -> 0.24911038 | K6: ='Data. Securities'!N8 -> 0.19097089
B7: SD of Residual (e), Firm specific Component | C7: ='Data. Securities'!F10 -> 0 | D7: ='Data. Securities'!G10 -> 0.22000089 | E7: ='Data. Securities'!H10 -> 0.53310342 | F7: ='Data. Securities'!I10 -> 0.15643099 | G7: ='Data. Securities'!J10 -> 0.34836694 | H7: ='Data. Securities'!K10 -> 0.22535098 | I7: ='Data. Securities'!L10 -> 0.15065167 | J7: ='Data. Securities'!M10 -> 0.20663502 | K7: ='Data. Securities'!N10 -> 0.16986841
B8: SD of Systematic Component | C8: =C5*$C$6 -> 0.18920755 | D8: =D5*$C$6 -> 0.21975048 | E8: =E5*$C$6 -> 0.33790336 | F8: =F5*$C$6 -> 0.1400029 | G8: =G5*$C$6 -> 0.21732732 | H8: =H5*$C$6 -> 0.19015769 | I8: =I5*$C$6 -> 0.16146613 | J8: =J5*$C$6 -> 0.13913286 | K8: =K5*$C$6 -> 0.087261696
B9: Correlation with the Market Index | C9: =C5*$C$6/C6 -> 1 | D9: =D5*$C$6/D6 -> 0.70670402 | E9: =E5*$C$6/E6 -> 0.53535365 | F9: =F5*$C$6/F6 -> 0.66689625 | G9: =G5*$C$6/G6 -> 0.52929469 | H9: =H5*$C$6/H6 -> 0.6449062 | I9: =I5*$C$6/I6 -> 0.73116831 | J9: =J5*$C$6/J6 -> 0.5585189 | K9: =K5*$C$6/K6 -> 0.45693716
B11: Panel B. Correlation Matrix | C11: =C4 -> IYC | D11: =D4 -> AMZN | E11: =E4 -> TSLA | F11: =F4 -> COST | G11: =G4 -> NFLX | H11: =H4 -> BKNG | I11: =I4 -> HD | J11: =J4 -> SBUX | K11: =K4 -> WMT
B12: {=TRANSPOSE(C11:K11)} -> IYC | C12: ='Data. Securities'!W7 -> 1
B13: AMZN | C13: ='Data. Securities'!W8 -> 0.70670402 | D13: ='Data. Securities'!X8 -> 1
B14: TSLA | C14: ='Data. Securities'!W9 -> 0.53535365 | D14: ='Data. Securities'!X9 -> 0.37833658 | E14: ='Data. Securities'!Y9 -> 1
B15: COST | C15: ='Data. Securities'!W10 -> 0.66689625 | D15: ='Data. Securities'!X10 -> 0.47129826 | E15: ='Data. Securities'!Y10 -> 0.35702534 | F15: ='Data. Securities'!Z10 -> 1
B16: NFLX | C16: ='Data. Securities'!W11 -> 0.52929469 | D16: ='Data. Securities'!X11 -> 0.37405469 | E16: ='Data. Securities'!Y11 -> 0.28335984 | F16: ='Data. Securities'!Z11 -> 0.35298464 | G16: ='Data. Securities'!AA11 -> 1
B17: BKNG | C17: ='Data. Securities'!W12 -> 0.6449062 | D17: ='Data. Securities'!X12 -> 0.45575781 | E17: ='Data. Securities'!Y12 -> 0.34525289 | F17: ='Data. Securities'!Z12 -> 0.43008552 | G17: ='Data. Securities'!AA12 -> 0.34134543 | H17: ='Data. Securities'!AB12 -> 1
B18: HD | C18: ='Data. Securities'!W13 -> 0.73116831 | D18: ='Data. Securities'!X13 -> 0.51671959 | E18: ='Data. Securities'!Y13 -> 0.39143362 | F18: ='Data. Securities'!Z13 -> 0.4876134 | G18: ='Data. Securities'!AA13 -> 0.3870035 | H18: ='Data. Securities'!AB13 -> 0.47153498 | I18: 1
B19: SBUX | C19: ='Data. Securities'!W14 -> 0.5585189 | D19: ='Data. Securities'!X14 -> 0.39470755 | E19: ='Data. Securities'!Y14 -> 0.29900513 | F19: ='Data. Securities'!Z14 -> 0.37247416 | G19: ='Data. Securities'!AA14 -> 0.29562109 | H19: ='Data. Securities'!AB14 -> 0.3601923 | I19: ='Data. Securities'!AC14 -> 0.40837132 | J19: 1
B20: WMT | C20: ='Data. Securities'!W15 -> 0.45693716 | D20: ='Data. Securities'!X15 -> 0.32291933 | E20: ='Data. Securities'!Y15 -> 0.24462297 | F20: ='Data. Securities'!Z15 -> 0.30472967 | G20: ='Data. Securities'!AA15 -> 0.24185441 | H20: ='Data. Securities'!AB15 -> 0.29468161 | I20: ='Data. Securities'!AC15 -> 0.33409797 | J20: ='Data. Securities'!AD15 -> 0.25520804 | K20: ='Data. Securities'!AE15 -> 1
B22: Panel C. The Index Model Covariance Matrix | C22: =C4 -> IYC | D22: =D4 -> AMZN | E22: =E4 -> TSLA | F22: =F4 -> COST | G22: =G4 -> NFLX | H22: =H4 -> BKNG | I22: =I4 -> HD | J22: =J4 -> SBUX | K22: =K4 -> WMT
B23: {=TRANSPOSE(C22:K22)} -> IYC | C23: ='Data. Securities'!W23 -> 0.035799496
B24: AMZN | C24: ='Data. Securities'!W24 -> 0.04157845 | D24: ='Data. Securities'!X24 -> 0.096690663
B25: TSLA | C25: ='Data. Securities'!W25 -> 0.063933866 | D25: ='Data. Securities'!X25 -> 0.074254426 | E25: ='Data. Securities'!Y25 -> 0.39838547
B26: COST | C26: ='Data. Securities'!W26 -> 0.026489605 | D26: ='Data. Securities'!X26 -> 0.030765704 | E26: ='Data. Securities'!Y26 -> 0.04730745 | F26: ='Data. Securities'!Z26 -> 0.044071468
B27: NFLX | C27: ='Data. Securities'!W27 -> 0.041119969 | D27: ='Data. Securities'!X27 -> 0.047757783 | E27: ='Data. Securities'!Y27 -> 0.073435632 | F27: ='Data. Securities'!Z27 -> 0.041119969 | G27: ='Data. Securities'!AA27 -> 0.16859069
B28: BKNG | C28: ='Data. Securities'!W28 -> 0.035979271 | D28: ='Data. Securities'!X28 -> 0.041787244 | E28: ='Data. Securities'!Y28 -> 0.064254923 | F28: ='Data. Securities'!Z28 -> 0.026622628 | G28: ='Data. Securities'!AA28 -> 0.041326462 | H28: ='Data. Securities'!AB28 -> 0.086943013
B29: HD | C29: ='Data. Securities'!W29 -> 0.030550611 | D29: ='Data. Securities'!X29 -> 0.03548226 | E29: ='Data. Securities'!Y29 -> 0.054559948 | F29: ='Data. Securities'!Z29 -> 0.022605726 | G29: ='Data. Securities'!AA29 -> 0.035091001 | H29: ='Data. Securities'!AB29 -> 0.030704027 | I29: ='Data. Securities'!AC29 -> 0.048767237
B30: SBUX | C30: ='Data. Securities'!W30 -> 0.026324987 | D30: ='Data. Securities'!X30 -> 0.030574512 | E30: ='Data. Securities'!Y30 -> 0.04701346 | F30: ='Data. Securities'!Z30 -> 0.019479003 | G30: ='Data. Securities'!AA30 -> 0.030237371 | H30: ='Data. Securities'!AB30 -> 0.026457183 | I30: ='Data. Securities'!AC30 -> 0.022465244 | J30: ='Data. Securities'!AD30 -> 0.062055983
B31: WMT | C31: ='Data. Securities'!W31 -> 0.016510572 | D31: ='Data. Securities'!X31 -> 0.0191758 | E31: ='Data. Securities'!Y31 -> 0.02948602 | F31: ='Data. Securities'!Z31 -> 0.01221689 | G31: ='Data. Securities'!AA31 -> 0.01896435 | H31: ='Data. Securities'!AB31 -> 0.016593483 | I31: ='Data. Securities'!AC31 -> 0.014089808 | J31: ='Data. Securities'!AD31 -> 0.012140969 | K31: ='Data. Securities'!AE31 -> 0.036469881
B33: Panel D. Correlation of Residuals in Pf A | C33: =C22 -> IYC | D33: =D22 -> AMZN | E33: =E22 -> TSLA | F33: =F22 -> COST | G33: =G22 -> NFLX | H33: =H22 -> BKNG | I33: =I22 -> HD | J33: =J22 -> SBUX | K33: =K22 -> WMT
B34: =B23 -> IYC
B35: =B24 -> AMZN | D35: ='Data. Securities'!X41 -> 1
B36: =B25 -> TSLA | D36: ='Data. Securities'!X42 -> 0.26088773 | E36: ='Data. Securities'!Y42 -> 1
B37: =B26 -> COST | D37: ='Data. Securities'!X43 -> 0.019469349 | E37: ='Data. Securities'!Y43 -> -0.12841119 | F37: ='Data. Securities'!Z43 -> 1
B38: =B27 -> NFLX | D38: ='Data. Securities'!X44 -> 0.30830061 | E38: ='Data. Securities'!Y44 -> -0.10310986 | F38: ='Data. Securities'!Z44 -> 0.017329326 | G38: ='Data. Securities'!AA44 -> 1
B39: =B28 -> BKNG | D39: ='Data. Securities'!X45 -> -0.40652006 | E39: ='Data. Securities'!Y45 -> -0.17503211 | F39: ='Data. Securities'!Z45 -> -0.16104884 | G39: ='Data. Securities'!AA45 -> -0.14038944 | H39: ='Data. Securities'!AB45 -> 1
B40: =B29 -> HD | D40: ='Data. Securities'!X46 -> -0.17725928 | E40: ='Data. Securities'!Y46 -> -0.11436499 | F40: ='Data. Securities'!Z46 -> 0.10925128 | G40: ='Data. Securities'!AA46 -> -0.17299556 | H40: ='Data. Securities'!AB46 -> -0.14972495 | I40: ='Data. Securities'!AC46 -> 1
B41: =B30 -> SBUX | D41: ='Data. Securities'!X47 -> -0.17951429 | E41: ='Data. Securities'!Y47 -> -0.24836382 | F41: ='Data. Securities'!Z47 -> 0.10414663 | G41: ='Data. Securities'!AA47 -> -0.11196059 | H41: ='Data. Securities'!AB47 -> 0.081086814 | I41: ='Data. Securities'!AC47 -> 0.030903431 | J41: ='Data. Securities'!AD47 -> 1
B42: =B31 -> WMT | D42: ='Data. Securities'!X48 -> -0.17013126 | E42: ='Data. Securities'!Y48 -> -0.04729219 | F42: ='Data. Securities'!Z48 -> 0.35381387 | G42: ='Data. Securities'!AA48 -> -0.13214638 | H42: ='Data. Securities'!AB48 -> -0.14690693 | I42: ='Data. Securities'!AC48 -> 0.025872186 | J42: ='Data. Securities'!AD48 -> -0.014073774 | K42: ='Data. Securities'!AE48 -> 1
B44: Panel E. Macro Forecast and Alpha Forecasts | C44: =C4 -> IYC | D44: =D4 -> AMZN | E44: =E4 -> TSLA | F44: =F4 -> COST | G44: =G4 -> NFLX | H44: =H4 -> BKNG | I44: =I4 -> HD | J44: =J4 -> SBUX | K44: =K4 -> WMT
B45: Adjusted Alpha | C45: ='Data. Securities'!F16 -> 0 | D45: ='Data. Securities'!G16 -> 0.12258895 | E45: ='Data. Securities'!H16 -> 0.067040669 | F45: ='Data. Securities'!I16 -> 0.058475126 | G45: ='Data. Securities'!J16 -> 0.1378241 | H45: ='Data. Securities'!K16 -> 0.068760739 | I45: ='Data. Securities'!L16 -> 0.04323193 | J45: ='Data. Securities'!M16 -> 0.0084348087 | K45: ='Data. Securities'!N16 -> 0.044231075
B46: Beta | C46: ='Data. Securities'!F17 -> 1 | D46: ='Data. Securities'!G17 -> 1.1614255 | E46: ='Data. Securities'!H17 -> 1.7858873 | F46: ='Data. Securities'!I17 -> 0.73994352 | G46: ='Data. Securities'!J17 -> 1.1486187 | H46: ='Data. Securities'!K17 -> 1.0050217 | I46: ='Data. Securities'!L17 -> 0.85338102 | J46: ='Data. Securities'!M17 -> 0.73534517 | K46: ='Data. Securities'!N17 -> 0.46119564
B47: Total Equity Risk Premium E(R) | C47: =C45+C46*$C$48 -> 0.070319413 | D47: =D45+D46*$C$48 -> 0.20425971 | E47: =E45+E46*$C$48 -> 0.19262322 | F47: =F45+F46*$C$48 -> 0.11050752 | G47: =G45+G46*$C$48 -> 0.21859429 | H47: =H45+H46*$C$48 -> 0.13943328 | I47: =I45+I46*$C$48 -> 0.10324118 | J47: =J45+J46*$C$48 -> 0.060143849 | K47: =K45+K46*$C$48 -> 0.076662081
B48: Adjusted Market risk premium = | C48: ='Data. Securities'!F7*'Data. Securities'!E27/'Data. Securities'!F27 -> 0.070319413
B50: Panel F. Active Portfolio | E50: Active Pf | F50: =D44 -> AMZN | G50: =E44 -> TSLA | H50: =F44 -> COST | I50: =G44 -> NFLX | J50: =H44 -> BKNG | K50: =I44 -> HD | L50: =J44 -> SBUX | M50: =K44 -> WMT
B51: Residual Variance of each security | C51: s2(e) | F51: =D7^2 -> 0.048400389 | G51: =E7^2 -> 0.28419926 | H51: =F7^2 -> 0.024470656 | I51: =G7^2 -> 0.12135952 | J51: =H7^2 -> 0.050783066 | K51: =I7^2 -> 0.022695926 | L51: =J7^2 -> 0.042698031 | M51: =K7^2 -> 0.028855277
B52: Initial position of each security | C52: wi(0) = ai/s2(e) | E52: =SUM(F52:M52) -> 11.283218 | F52: =D45/F51 -> 2.5328092 | G52: =E45/G51 -> 0.23589319 | H52: =F45/H51 -> 2.3896019 | I52: =G45/I51 -> 1.1356678 | J52: =H45/J51 -> 1.3540092 | K52: =I45/K51 -> 1.9048322 | L52: =J45/L51 -> 0.19754561 | M52: =K45/M51 -> 1.5328591
B53: Scaled initial position of each security | C53: wi | E53: =SUM(F53:M53) -> 1 | F53: =F52/$E$52 -> 0.22447578 | G53: =G52/$E$52 -> 0.020906552 | H53: =H52/$E$52 -> 0.21178372 | I53: =I52/$E$52 -> 0.10065105 | J53: =J52/$E$52 -> 0.12000204 | K53: =K52/$E$52 -> 0.16881994 | L53: =L52/$E$52 -> 0.017507914 | M53: =M52/$E$52 -> 0.13585301
B54: Squared scaled initial position of each security | C54: [wi(0)]2 | F54: =F53^2 -> 0.050389375 | G54: =G53^2 -> 0.00043708391 | H54: =H53^2 -> 0.044852343 | I54: =I53^2 -> 0.010130635 | J54: =J53^2 -> 0.01440049 | K54: =K53^2 -> 0.028500171 | L54: =L53^2 -> 0.00030652705 | M54: =M53^2 -> 0.018456039
B55: Alpha of the Active Pf | C55: aA | E55: =SUMPRODUCT(D45:K45,F53:M53) -> 0.076882501
B56: Residual Variance of Active Pf | C56: s2(eA) | E56: =SUMPRODUCT(F51:M51,F54:M54) -> 0.0068138806
B57: Active Pf information ratio (APIR) | C57: aA / s2(eA) | E57: =E55/E56 -> 11.283218
B58: Index Pf information ratio (IPIR) | C58: E(RM)/s2(M) | E58: =C47/C6^2 -> 1.964257
B59: Initial position in Active Pf (APIR/IPIR) | C59: wA(0) | E59: =E57/E58 -> 5.7442677
B60: Beta of the Active Pf | C60: bA | E60: =SUMPRODUCT(D46:K46,F53:M53) -> 0.91056787
B62: Panel G. Optimal Risky Portfolios | C62: Overall Risky Pf | D62: =C44 -> IYC | E62: Active Pf | F62: =F50 -> AMZN | G62: =G50 -> TSLA | H62: =H50 -> COST | I62: =I50 -> NFLX | J62: =J50 -> BKNG | K62: =K50 -> HD | L62: =L50 -> SBUX | M62: =M50 -> WMT
B63: w*(Optimal Pf): Short not allowed | C63: 1 | D63: =C63-E63 -> 0 | E63: 1 | F63: =$E$63*F53 -> 0.22447578 | G63: =$E$63*G53 -> 0.020906552 | H63: =$E$63*H53 -> 0.21178372 | I63: =$E$63*I53 -> 0.10065105 | J63: =$E$63*J53 -> 0.12000204 | K63: =$E$63*K53 -> 0.16881994 | L63: =$E$63*L53 -> 0.017507914 | M63: =$E$63*M53 -> 0.13585301
B64: Beta | C64: =D64*D63+E64*E63 -> 0.91056787 | D64: =1 -> 1 | E64: =SUMPRODUCT(D46:K46,F53:M53) -> 0.91056787
B65: Risk Premium | C65: =D65*D63+E65*E63 -> 0.1409131 | D65: =C47 -> 0.070319413 | E65: =SUMPRODUCT(D47:K47,F53:M53) -> 0.1409131
B66: Standard Deviation | C66: =SQRT((D63+E63*E60)^2*D66^2+E63^2*E56) -> 0.19104045 | D66: =C6 -> 0.18920755 | E66: =SQRT(E60^2*C6^2+E56) -> 0.19104045
B67: Sharpe Ratio (S) | C67: =C65/C66 -> 0.73760869 | D67: =D65/D66 -> 0.37165226 | E67: =E65/E66 -> 0.73760869
B68: Performance Measures
B69: Treynor Measure (T) | C69: =C65/C64 -> 0.15475299 | D69: =D65/D64 -> 0.070319413 | E69: =E65/E64 -> 0.15475299
B70: Jensen Measure (a) | C70: =SUMPRODUCT($D$63*D70+$E$63*E70) -> 0.076882501 | D70: 0 | E70: =E55 -> 0.076882501
B71: Information Ratio Measure (IR) | C71: =SUMPRODUCT($D$63*D71+$E$63*E71) -> 0.36952219 | D71: 0 | E71: =(E65-D65)/E66 -> 0.36952219
B72: Overall Performance | C72: =SUMPRODUCT($D$63*D72+$E$63*E72) -> 0.1409131 | D72: =D65 -> 0.070319413 | E72: =E65 -> 0.1409131
B73: CAPM | C73: =SUMPRODUCT($D$63*D73+$E$63*E73) -> 0.1064906 | D73: =5%+$C$48*D64 -> 0.12031941 | E73: =4.246%+$C$48*E64 -> 0.1064906
B74: Ratio of total risk (𝜎p/𝜎m) | C74: =SUMPRODUCT($D$63*D74+$E$63*E74) -> 1.0096873 | D74: =D66/$D$66 -> 1 | E74: =E66/$D$66 -> 1.0096873
B75: CML | C75: =SUMPRODUCT($D$63*D75+$E$63*E75) -> 0.11346062 | D75: =5%+$C$48*D74 -> 0.12031941 | E75: =4.246%+$C$48*E74 -> 0.11346062
B76: Selectivity (%) | C76: =SUMPRODUCT($D$63*D76+$E$63*E76) -> 0.076882501 | D76: =D65+5%-D73 -> 0 | E76: =E65+4.246%-E73 -> 0.076882501
B77: Diversification Effect (%) | C77: =SUMPRODUCT($D$63*D77+$E$63*E77) -> -0.006970018 | D77: =D73-D75 -> 0 | E77: =E73-E75 -> -0.006970018
B78: Net Selectivity (%) | C78: =SUMPRODUCT($D$63*D78+$E$63*E78) -> 0.083852519 | D78: =D76-D77 -> 0 | E78: =E76-E77 -> 0.083852519
B79: net Risk Premium of Pf | C79: =SUMPRODUCT($D$63*D79+$E$63*E79) -> 0.064030599 | D79: =D72-D76 -> 0.070319413 | E79: =E72-E76 -> 0.064030599

Sheet Data. Securities
B2: Data. Security Index Model
B4: Panel 1. Risk & Return Parameters in the Security Index Model | U4: Panel 2. Correlation and Covariance Matrixs in the Security Index Model
B6: Estimates annualized | E6: T-bill | F6: IYC | G6: AMZN | H6: TSLA | I6: COST | J6: NFLX | K6: BKNG | L6: HD | M6: SBUX | N6: WMT | O6: IGSB | V6: Correl (via Index) | W6: =F6 -> IYC | X6: =G6 -> AMZN | Y6: =H6 -> TSLA | Z6: =I6 -> COST | AA6: =J6 -> NFLX | AB6: =K6 -> BKNG | AC6: =L6 -> HD | AD6: =M6 -> SBUX | AE6: =N6 -> WMT
B7: Expected excess return | E7: 0.04246 | F7: =AVERAGE(E57:E176)*12 -> 0.065117414 | G7: =AVERAGE(H57:H176)*12 -> 0.2390791 | H7: =AVERAGE(M57:M176)*12 -> 0.44280844 | I7: =AVERAGE(R57:R176)*12 -> 0.17290167 | J7: =AVERAGE(W57:W176)*12 -> 0.32314709 | K7: =AVERAGE(AB57:AB176)*12 -> 0.13895424 | L7: =AVERAGE(AG57:AG176)*12 -> 0.099386223 | M7: =AVERAGE(AL57:AL176)*12 -> 0.061304652 | N7: =AVERAGE(AQ57:AQ176)*12 -> 0.09267216 | O7: =AVERAGE(AX57:AX176)*12 -> -0.042807137 | V7: IYC | W7: 1
B8: SD of Excess Return | F8: =_xlfn.STDEV.S(E57:E176)*SQRT(12) -> 0.18920755 | G8: =_xlfn.STDEV.S(H57:H176)*SQRT(12) -> 0.31095122 | H8: =_xlfn.STDEV.S(M57:M176)*SQRT(12) -> 0.63117784 | I8: =_xlfn.STDEV.S(R57:R176)*SQRT(12) -> 0.20993206 | J8: =_xlfn.STDEV.S(W57:W176)*SQRT(12) -> 0.41059796 | K8: =_xlfn.STDEV.S(AB57:AB176)*SQRT(12) -> 0.29486101 | L8: =_xlfn.STDEV.S(AG57:AG176)*SQRT(12) -> 0.22083305 | M8: =_xlfn.STDEV.S(AL57:AL176)*SQRT(12) -> 0.24911038 | N8: =_xlfn.STDEV.S(AQ57:AQ176)*SQRT(12) -> 0.19097089 | O8: =_xlfn.STDEV.S(AX57:AX176)*SQRT(12) -> 0.028165402 | V8: =X6 -> AMZN | W8: =G18 -> 0.70670402 | X8: 1
B9: Sharpe Ratio | F9: =F7/F8 -> 0.34415865 | G9: =G7/G8 -> 0.76886368 | H9: =H7/H8 -> 0.70155891 | I9: =I7/I8 -> 0.82360776 | J9: =J7/J8 -> 0.78701582 | K9: =K7/K8 -> 0.47125334 | L9: =L7/L8 -> 0.45005139 | M9: =M7/M8 -> 0.24609433 | ... O9: =O7/O8 -> -1.5198483 | V9: =Y6 -> TSLA | W9: =H18 -> 0.53535365 | X9: =G18*H18 -> 0.37833658 | Y9: 1
B10: SD of Residuals (e) | F10: 0 | G10: =_xlfn.STDEV.S(J57:J176)*SQRT(12) -> 0.22000089 | H10: =_xlfn.STDEV.S(O57:O176)*SQRT(12) -> 0.53310342 | I10: =_xlfn.STDEV.S(T57:T176)*SQRT(12) -> 0.15643099 | J10: =_xlfn.STDEV.S(Y57:Y176)*SQRT(12) -> 0.34836694 | K10: =_xlfn.STDEV.S(AD57:AD176)*SQRT(12) -> 0.22535098 | L10: =_xlfn.STDEV.S(AI57:AI176)*SQRT(12) -> 0.15065167 | M10: =_xlfn.STDEV.S(AN57:AN176)*SQRT(12) -> 0.20663502 | N10: =_xlfn.STDEV.S(AS57:AS176)*SQRT(12) -> 0.16986841 | V10: =Z6 -> COST | W10: =I18 -> 0.66689625 | X10: =G18*I18 -> 0.47129826 | Y10: =H18*I18 -> 0.35702534 | Z10: 1
B11: SD of Systematic component | F11: =F8 -> 0.18920755 | G11: =_xlfn.STDEV.S(I57:I176)*SQRT(12) -> 0.21975048 | H11: =_xlfn.STDEV.S(N57:N176)*SQRT(12) -> 0.33790336 | I11: =_xlfn.STDEV.S(S57:S176)*SQRT(12) -> 0.1400029 | J11: =_xlfn.STDEV.S(X57:X176)*SQRT(12) -> 0.21732732 | K11: =_xlfn.STDEV.S(AC57:AC176)*SQRT(12) -> 0.19015769 | L11: =_xlfn.STDEV.S(AH57:AH176)*SQRT(12) -> 0.16146613 | M11: =_xlfn.STDEV.S(AM57:AM176)*SQRT(12) -> 0.13913286 | N11: =_xlfn.STDEV.S(AR57:AR176)*SQRT(12) -> 0.087261696 | V11: =AA6 -> NFLX | W11: =J18 -> 0.52929469 | X11: =G18*J18 -> 0.37405469 | Y11: =H18*J18 -> 0.28335984 | Z11: =I18*J18 -> 0.35298464 | AA11: 1
B12: Covariance | F12: =F8^2 -> 0.035799496 | G12: =_xlfn.COVARIANCE.P($E$57:$E$176,H57:H176)*12 -> 0.041231963 | H12: =_xlfn.COVARIANCE.P($E$57:$E$176,M57:M176)*12 -> 0.063401084 | I12: =_xlfn.COVARIANCE.P($E$57:$E$176,R57:R176)*12 -> 0.026268859 | J12: =_xlfn.COVARIANCE.P($E$57:$E$176,W57:W176)*12 -> 0.040777303 | K12: =_xlfn.COVARIANCE.P($E$57:$E$176,AB57:AB176)*12 -> 0.035679444 | L12: =_xlfn.COVARIANCE.P($E$57:$E$176,AG57:AG176)*12 -> 0.030296022 | M12: =_xlfn.COVARIANCE.P($E$57:$E$176,AL57:AL176)*12 -> 0.026105612 | N12: =_xlfn.COVARIANCE.P($E$57:$E$176,AQ57:AQ176)*12 -> 0.016372983 | V12: =AB6 -> BKNG | W12: =K18 -> 0.6449062 | X12: =G18*K18 -> 0.45575781 | Y12: =H18*K18 -> 0.34525289 | Z12: =I18*K18 -> 0.43008552 | AA12: =J18*K18 -> 0.34134543 | AB12: 1
B13: Alpha (Non-market risk premium in the index model) | F13: 0 | G13: =INTERCEPT(H57:H176,$E$57:$E$176)*12 -> 0.16345007 | H13: =INTERCEPT(M57:M176,$E$57:$E$176)*12 -> 0.32651608 | I13: =INTERCEPT(R57:R176,$E$57:$E$176)*12 -> 0.12471846 | J13: =INTERCEPT(W57:W176,$E$57:$E$176)*12 -> 0.24835202 | K13: =INTERCEPT(AB57:AB176,$E$57:$E$176)*12 -> 0.073509822 | L13: =INTERCEPT(AG57:AG176,$E$57:$E$176)*12 -> 0.043816258 | M13: =INTERCEPT(AL57:AL176,$E$57:$E$176)*12 -> 0.013420877 | N13: =INTERCEPT(AQ57:AQ176,$E$57:$E$176)*12 -> 0.062640293 | V13: HD | W13: =L18 -> 0.73116831 | X13: =G18*L18 -> 0.51671959 | Y13: =H18*L18 -> 0.39143362 | Z13: =I18*L18 -> 0.4876134 | AA13: =J18*L18 -> 0.3870035 | AB13: =K18*L18 -> 0.47153498 | AC13: 1
B14: Adjusted Alpha (a x avg. Market PE / Stock PE) | F14: 0 | G14: =G13*$E$27/G27 -> 0.12675234 | H14: =H13*$E$27/H27 -> 0.068779649 | I14: =I13*$E$27/I27 -> 0.060124052 | J14: =J13*$E$27/J27 -> 0.14083506 | K14: =K13*$E$27/K27 -> 0.073399571 | L14: =L13*$E$27/L27 -> 0.047509241 | M14: =M13*$E$27/M27 -> 0.011295763 | N14: =N13*$E$27/N27 -> 0.045789486 | V14: SBUX | W14: =M18 -> 0.5585189 | X14: =G18*M18 -> 0.39470755 | Y14: =H18*M18 -> 0.29900513 | Z14: =I18*M18 -> 0.37247416 | AA14: =J18*M18 -> 0.29562109 | AB14: =K18*M18 -> 0.3601923 | AC14: =L18*M18 -> 0.40837132 | AD14: 1
B15: Alpha in CAPM (10 yrs market premium) | F15: 0 | G15: =(G7+$E$7-(4.246%+G17*(11.22%-4.246%))) -> 0.15808128 | H15: =(H7+$E$7-(4.246%+H17*(11.22%-4.246%))) -> 0.31826066 | I15: =(I7+$E$7-(4.246%+I17*(11.22%-4.246%))) -> 0.12129801 | J15: =(J7+$E$7-(4.246%+J17*(11.22%-4.246%))) -> 0.24304243 | K15: =(K7+$E$7-(4.246%+K17*(11.22%-4.246%))) -> 0.068864022 | L15: =(L7+$E$7-(4.246%+L17*(11.22%-4.246%))) -> 0.039871431 | M15: =(M7+$E$7-(4.246%+M17*(11.22%-4.246%))) -> 0.01002168 | N15: =(N7+$E$7-(4.246%+N17*(11.22%-4.246%))) -> 0.060508376 | V15: WMT | W15: =N18 -> 0.45693716 | X15: =G18*N18 -> 0.32291933 | Y15: =H18*N18 -> 0.24462297 | Z15: =I18*N18 -> 0.30472967 | AA15: =J18*N18 -> 0.24185441 | AB15: =K18*N18 -> 0.29468161 | AC15: =L18*N18 -> 0.33409797 | AD15: =M18*N18 -> 0.25520804 | AE15: 1
B16: Adjusted Alpha in CAPM (a x avg. Market PE / Stock PE) | F16: 0 | G16: =G15*$E$27/G27 -> 0.12258895 | H16: =H15*$E$27/H27 -> 0.067040669 | I16: =I15*$E$27/I27 -> 0.058475126 | J16: =J15*$E$27/J27 -> 0.1378241 | K16: =K15*$E$27/K27 -> 0.068760739 | L16: =L15*$E$27/L27 -> 0.04323193 | M16: =M15*$E$27/M27 -> 0.0084348087 | N16: =N15*$E$27/N27 -> 0.044231075
B17: Beta | F17: 1 | G17: =SLOPE(H57:H176,$E$57:$E$176) -> 1.1614255 | H17: =SLOPE(M57:M176,$E$57:$E$176) -> 1.7858873 | I17: =SLOPE(R57:R176,$E$57:$E$176) -> 0.73994352 | J17: =SLOPE(W57:W176,$E$57:$E$176) -> 1.1486187 | K17: =SLOPE(AB57:AB176,$E$57:$E$176) -> 1.0050217 | L17: =SLOPE(AG57:AG176,$E$57:$E$176) -> 0.85338102 | M17: =SLOPE(AL57:AL176,$E$57:$E$176) -> 0.73534517 | N17: =SLOPE(AQ57:AQ176,$E$57:$E$176) -> 0.46119564
B18: Correlation with Index | F18: 1 | G18: =CORREL(H57:H176,$E$57:$E$176) -> 0.70670402 | H18: =CORREL(M57:M176,$E$57:$E$176) -> 0.53535365 | I18: =CORREL(R57:R176,$E$57:$E$176) -> 0.66689625 | J18: =CORREL(W57:W176,$E$57:$E$176) -> 0.52929469 | K18: =CORREL(AB57:AB176,$E$57:$E$176) -> 0.6449062 | L18: =CORREL(AG57:AG176,$E$57:$E$176) -> 0.73116831 | M18: =CORREL(AL57:AL176,$E$57:$E$176) -> 0.5585189 | N18: =CORREL(AQ57:AQ176,$E$57:$E$176) -> 0.45693716 | P18: =CORREL(E57:E176,AX57:AX176) -> 0.53898049
B19: R Squared (Market Determination) | F19: 1 | G19: =G18^2 -> 0.49943058 | H19: =H18^2 -> 0.28660353 | I19: =I18^2 -> 0.4447506 | J19: =J18^2 -> 0.28015287 | K19: =K18^2 -> 0.41590401 | L19: =L18^2 -> 0.5346071 | M19: =M18^2 -> 0.31194336 | N19: =N18^2 -> 0.20879157
B20: 1-R Squared (Firms Specific) | F20: 1 | G20: =1-G19 -> 0.50056942 | H20: =1-H19 -> 0.71339647 | I20: =1-I19 -> 0.5552494 | J20: =1-J19 -> 0.71984713 | K20: =1-K19 -> 0.58409599 | L20: =1-L19 -> 0.4653929 | M20: =1-M19 -> 0.68805664 | N20: =1-N19 -> 0.79120843
B21: Pf Style. | C21: Value / Blend / Growth | F21: Large Growth | G21: Growth | H21: Growth | I21: Blend | J21: Growth | K21: Growth | L21: Blend | M21: Growth | N21: Blend | P21: Credit (Investment / High Yield)
C22: Small / Medium / Large | G22: Large | H22: Large | I22: Large | J22: Large | K22: Large | L22: Large | M22: Large | N22: Large | P22: Duration (longer / shorter) | V22: Covariance (via Index) | W22: =W6 -> IYC | X22: =X6 -> AMZN | Y22: =Y6 -> TSLA | Z22: =Z6 -> COST | AA22: =AA6 -> NFLX | AB22: =AB6 -> BKNG | AC22: =AC6 -> HD | AD22: =AD6 -> SBUX | AE22: =AE6 -> WMT
C23: Sector (industry) | G23: Consumer Discretionary | H23: Consumer Discretionary | I23: Consumer Staples | J23: Communication | K23: Consumer Discretionary | L23: Consumer Discretionary | M23: Consumer Discretionary | N23: Consumer Staples | P23: Issuers (Corporate / Government) | V23: IYC | W23: =F8^2 -> 0.035799496
C24: Themes | G24: E commerce | H24: Renewable Energy | I24: Retail | J24: Streaming | K24: Travel | L24: Retail | M24: Retail | N24: Retail | P24: Inflation / close-ended / sector… | V24: =X22 -> AMZN | W24: =G17*1*W23 -> 0.04157845 | X24: =G8^2 -> 0.096690663
B25: Stock Info. | C25: Current Stock Price (as of March 31st) | G25: 190.26 | H25: 259.16 | I25: 945.78 | J25: 932.52 | K25: 4606.91 | L25: 366.49 | M25: 98.09 | N25: 87.79 | V25: =Y22 -> TSLA | W25: =$H$17*$W$23 -> 0.063933866 | X25: =$H$17*G17*$W$23 -> 0.074254426 | Y25: =H8^2 -> 0.39838547
C26: EPS (TTM) | G26: 5.54 | H26: 2.05 | I26: 17.12 | J26: 19.86 | K26: 172.76 | L26: 14.92 | M26: 3.1 | N26: 2.41 | V26: =Z22 -> COST | W26: =$I$17*1*$W$23 -> 0.026489605 | X26: =$I$17*G17*$W$23 -> 0.030765704 | Y26: =$I$17*H17*$W$23 -> 0.04730745 | Z26: =I8^2 -> 0.044071468
C27: PE Ratio (TTM) | E27: 26.63 | F27: 24.66 | G27: 34.34 | H27: 126.42 | I27: 55.24 | J27: 46.96 | K27: 26.67 | L27: 24.56 | M27: 31.64 | N27: 36.43 | V27: =AA22 -> NFLX | W27: =$J$17*$W$23 -> 0.041119969 | X27: =$J$17*$W$23*G17 -> 0.047757783 | Y27: =$J$17*$W$23*H17 -> 0.073435632 | Z27: =$J$17*$W$23 -> 0.041119969 | AA27: =J8^2 -> 0.16859069
C28: 1y Forward Dividend ($) | I28: 4.64 | K28: 38.4 | L28: 9.2 | M28: 2.44 | N28: 0.94 | V28: =AB22 -> BKNG | W28: =$K$17*$W$23 -> 0.035979271 | X28: =$K$17*$W$23*G17 -> 0.041787244 | Y28: =$K$17*$W$23*H17 -> 0.064254923 | Z28: =$K$17*$W$23*I17 -> 0.026622628 | AA28: =$K$17*$W$23*J17 -> 0.041326462 | AB28: =K8^2 -> 0.086943013
C29: 1y Forward Dividend Yield (%) | I29: 0.0049 | K29: 0.0083 | L29: 0.0251 | M29: 0.0249 | N29: 0.0107 | V29: HD | W29: =$L$17*$W$23 -> 0.030550611 | X29: =$L$17*$W$23*G17 -> 0.03548226 | Y29: =$L$17*$W$23*H17 -> 0.054559948 | Z29: =$L$17*$W$23*I17 -> 0.022605726 | AA29: =$L$17*$W$23*J17 -> 0.035091001 | AB29: =$L$17*$W$23*K17 -> 0.030704027 | AC29: =L8^2 -> 0.048767237
C30: 1y Target Est. (Consensus) | G30: 264.59 | H30: 329.91 | I30: 1063.16 | J30: 1073.96 | K30: 5636.98 | L30: 431.5 | M30: 107.51 | N30: 108.11 | V30: SBUX | W30: =$M$17*$W$23 -> 0.026324987 | X30: =$M$17*$W$23*G17 -> 0.030574512 | Y30: =$M$17*$W$23*H17 -> 0.04701346 | Z30: =$M$17*$W$23*I17 -> 0.019479003 | AA30: =$M$17*$W$23*J17 -> 0.030237371 | AB30: =$M$17*$W$23*K17 -> 0.026457183 | AC30: =$M$17*$W$23*L17 -> 0.022465244 | AD30: =M8^2 -> 0.062055983
C31: 1y Target return ` | G31: =(G30-G25)/G25 -> 0.39067592 | H31: =(H30-H25)/H25 -> 0.27299738 | I31: =(I30-I25)/I25 -> 0.1241092 | J31: =(J30-J25)/J25 -> 0.15167503 | K31: =(K30-K25)/K25 -> 0.22359239 | L31: =(L30-L25)/L25 -> 0.17738547 | M31: =(M30-M25)/M25 -> 0.096034254 | N31: =(N30-N25)/N25 -> 0.23146144 | V31: WMT | W31: =$N$17*$W$23 -> 0.016510572 | X31: =$N$17*$W$23*G17 -> 0.0191758 | Y31: =$N$17*$W$23*H17 -> 0.02948602 | Z31: =$N$17*$W$23*I17 -> 0.01221689 | AA31: =$N$17*$W$23*J17 -> 0.01896435 | AB31: =$N$17*$W$23*K17 -> 0.016593483 | AC31: =$N$17*$W$23*L17 -> 0.014089808 | AD31: =$N$17*$W$23*M17 -> 0.012140969 | AE31: =N8^2 -> 0.036469881
B32: Active Pf Weights* (Index model) | F32: ='Security Allocation'!D63 -> 0 | G32: ='Security Allocation'!F63 -> 0.22447578 | H32: ='Security Allocation'!G63 -> 0.020906552 | I32: ='Security Allocation'!H63 -> 0.21178372 | J32: ='Security Allocation'!I63 -> 0.10065105 | K32: ='Security Allocation'!J63 -> 0.12000204 | L32: ='Security Allocation'!K63 -> 0.16881994 | M32: ='Security Allocation'!L63 -> 0.017507914 | N32: ='Security Allocation'!M63 -> 0.13585301 | ... R32: ='Security Allocation'!Q63 -> 0
V39: Correl of Residuals | W39: =W6 -> IYC | X39: =X6 -> AMZN | Y39: =Y6 -> TSLA | Z39: =Z6 -> COST | AA39: =AA6 -> NFLX | AB39: =AB6 -> BKNG | AC39: =AC6 -> HD | AD39: =AD6 -> SBUX | AE39: =AE6 -> WMT
V40: IYC
V41: =X39 -> AMZN | X41: 1
V42: =Y39 -> TSLA | X42: =CORREL(J57:J115,O57:O115) -> 0.26088773 | Y42: 1
V43: =Z39 -> COST | X43: =CORREL(J57:J115,T57:T115) -> 0.019469349 | Y43: =CORREL(O57:O115,T57:T115) -> -0.12841119 | Z43: 1
V44: =AA39 -> NFLX | X44: =CORREL(J57:J115,Y57:Y115) -> 0.30830061 | Y44: =CORREL(O57:O115,Y57:Y115) -> -0.10310986 | Z44: =CORREL(T57:T115,Y57:Y115) -> 0.017329326 | AA44: 1
V45: =AB39 -> BKNG | X45: =CORREL(J57:J115,AD57:AD115) -> -0.40652006 | Y45: =CORREL(O57:O115,AD57:AD115) -> -0.17503211 | Z45: =CORREL(T57:T115,AD57:AD115) -> -0.16104884 | AA45: =CORREL(Y57:Y115,AD57:AD115) -> -0.14038944 | AB45: 1
V46: HD | X46: =CORREL(J57:J176,AI57:AI176) -> -0.17725928 | Y46: =CORREL(O57:O176,AI57:AI176) -> -0.11436499 | Z46: =CORREL(T57:T176,AI57:AI176) -> 0.10925128 | AA46: =CORREL(Y57:Y176,AI57:AI176) -> -0.17299556 | AB46: =CORREL(AI57:AI176,AD57:AD176) -> -0.14972495 | AC46: 1
V47: SBUX | X47: =CORREL($AN$57:$AN$176,J57:J176) -> -0.17951429 | Y47: =CORREL($AN$57:$AN$176,O57:O176) -> -0.24836382 | Z47: =CORREL($AN$57:$AN$176,T57:T176) -> 0.10414663 | AA47: =CORREL($AN$57:$AN$176,Y57:Y176) -> -0.11196059 | AB47: =CORREL($AN$57:$AN$176,AD57:AD176) -> 0.081086814 | AC47: =CORREL($AN$57:$AN$176,AI57:AI176) -> 0.030903431 | AD47: 1
V48: WMT | X48: =CORREL($AS$57:$AS$176,J57:J176) -> -0.17013126 | Y48: =CORREL($AS$57:$AS$176,O57:O176) -> -0.04729219 | Z48: =CORREL($AS$57:$AS$176,T57:T176) -> 0.35381387 | AA48: =CORREL($AS$57:$AS$176,Y57:Y176) -> -0.13214638 | AB48: =CORREL($AS$57:$AS$176,AD57:AD176) -> -0.14690693 | AC48: =CORREL($AS$57:$AS$176,AI57:AI176) -> 0.025872186 | AD48: =CORREL($AS$57:$AS$176,AN57:AN176) -> -0.014073774 | AE48: 1
B54: 120 months | C54: iShares U.S. Consumer Discretionary ETF (IYC) | F54: Amazon (AMZN) | K54: Tesla (TSLA) | P54: Costco (COST) | U54: Netflix (NFLX) | Z54: Booking Holdings (BKNG) | AE54: Home Depot (HD) | AJ54: Starbucks (SBUX) | AO54: Walmart (WMT) | AT54: Equity Pf | AV54: Bond Pf (IGSB) | AZ54: Benchmark Check
B55: Dates | C55: Prices | D55: Monthly rate | E55: Benchmark Exces return | F55: Prices | G55: Monthly rate | H55: Excess return | I55: Mkt Prem. Systematic component | J55: Residuals. Unsystematic component | K55: Prices | L55: Monthly rate | M55: Exces return | N55: Mkt Prem. Systematic component | O55: Residuals. Unsystematic component | P55: Prices | Q55: Monthly rate | R55: Exces return | S55: Mkt Prem. Systematic component | T55: Residuals. Unsystematic component | U55: Prices | V55: Monthly rate | W55: Exces return | X55: Mkt Prem. Systematic component | Y55: Residuals. Unsystematic component | Z55: Prices | AA55: Monthly rate | AB55: Excess return | AC55: Mkt Prem. Systematic component | AD55: Residuals. Unsystematic component | AE55: Prices | AF55: Monthly rate | AG55: Excess return | AH55: Mkt Prem. Systematic component | AI55: Residuals. Unsystematic component | AJ55: Prices | AK55: Monthly rate | AL55: Excess return | AM55: Mkt Prem. Systematic component | AN55: Residuals. Unsystematic component | AO55: Prices | AP55: Monthly rate | AQ55: Excess return | AR55: Mkt Prem. Systematic component | AS55: Residuals. Unsystematic component | AT55: Adjusted Price of Equity Pf (Back data) | AU55: Active Pf Exces return (Back data) | AV55: Prices | AW55: Monthly rate | AX55: Exces return | AZ55: Active Pf Excess Retun - Benchmark (Back Data)
B56: 45660 | C56: 88.32 | F56: 190.26 | K56: 259.16 | P56: 945.78 | U56: 932.53 | Z56: 4606.91 | AE56: 366.49 | AJ56: 98.09 | AO56: 87.79 | AT56: =AT57*(1+AU56) -> 171.84987 | AV56: 52.37
B57: 45659 | C57: 96.38 | D57: =(C56-C57)/C57 -> -0.083627309 | E57: =D57-$E$7/12 -> -0.087165642 | F57: 212.28 | G57: =(F56-F57)/F57 -> -0.10373092 | H57: =G57-$E$7/12 -> -0.10726925 | I57: =$G$17*E57 -> -0.1012364 | J57: =H57-$G$13/12-I57 -> -0.019653691 | K57: 292.98 | L57: =(K56-K57)/K57 -> -0.1154345 | M57: =L57-$E$7/12 -> -0.11897283 | N57: =$H$17*E57 -> -0.15566801 | O57: =M57-$H$13/12-N57 -> 0.0094855063 | P57: 1048.61 | Q57: =(P56-P57)/P57 -> -0.09806315 | R57: =Q57-$E$7/12 -> -0.10160148 | S57: =E57*$I$17 -> -0.064497652 | T57: =R57-$I$13/12-S57 -> -0.047497037 | U57: 980.56 | V57: =(U56-U57)/U57 -> -0.048982214 | W57: =V57-$E$7/12 -> -0.052520548 | X57: =E57*$J$17 -> -0.10012008 | Y57: =W57-$J$13/12-X57 -> 0.026903533 | Z57: 5016.01 | AA57: =(Z56-Z57)/Z57 -> -0.081558849 | AB57: =AA57-$E$7/12 -> -0.085097182 | AC57: =E57*$K$17 -> -0.087603362 | AD57: =AB57-$K$13/12-AC57 -> -0.0036196388 | AE57: 396.6 | AF57: =(AE56-AE57)/AE57 -> -0.075920323 | AG57: =AF57-$E$7/12 -> -0.079458656 | AH57: =E57*$L$17 -> -0.074385504 | AI57: =AG57-$L$13/12-AH57 -> -0.0087245066 | AJ57: 115.81 | AK57: =(AJ56-AJ57)/AJ57 -> -0.15300924 | AL57: =AK57-$E$7/12 -> -0.15654757 | AM57: =E57*$M$17 -> -0.064096833 | AN57: =AL57-$M$13/12-AM57 -> -0.093569146 | AO57: 98.61 | AP57: =(AO56-AO57)/AO57 -> -0.10972518 | AQ57: =AP57-$E$7/12 -> -0.11326351 | AR57: =E57*$N$17 -> -0.040200414 | AS57: =AQ57-$N$13/12-AR57 -> -0.078283124 | AT57: =AT58*(1+AU57) -> 171.84987 | AU57: =$F$32*E57+$G$32*H57+$H$32*M57+$I$32*R57+$J$32*W57+$K$32*AB57+$L$32*AG57+$M$32*AL57+$N$32*AQ57 -> -0.095124501 | AV57: 52.35 | AW57: =(AV56-AV57)/AV57 -> 0.00038204394 | AX57: =AW57-$E$7/12 -> -0.0031562894 | AZ57: =E57-AX57 -> -0.084009353
B58: 45658 | C58: 100.57 | D58: =(C57-C58)/C58 -> -0.041662524 | E58: =D58-$E$7/12 -> -0.045200857 | F58: 237.68 | G58: =(F57-F58)/F58 -> -0.10686637 | H58: =G58-$E$7/12 -> -0.11040471 | I58: =$G$17*E58 -> -0.05249743 | J58: =H58-$G$13/12-I58 -> -0.071528118 | K58: 404.6 | L58: =(K57-K58)/K58 -> -0.27587741 | M58: =L58-$E$7/12 -> -0.27941574 | N58: =$H$17*E58 -> -0.080723637 | O58: =M58-$G$13/12-N58 -> -0.21231295 | P58: 979.88 | Q58: =(P57-P58)/P58 -> 0.070141242 | R58: =Q58-$E$7/12 -> 0.066602908 | S58: =E58*$I$17 -> -0.033446081 | T58: =R58-$I$13/12-S58 -> 0.089655784 | U58: 976.76 | V58: =(U57-U58)/U58 -> 0.0038904132 | W58: =V58-$E$7/12 -> 0.00035207987 | X58: =E58*$J$17 -> -0.051918547 | Y58: =W58-$J$13/12-X58 -> 0.031574626 | Z58: 4737.56 | AA58: =(Z57-Z58)/Z58 -> 0.058774981 | AB58: =AA58-$E$7/12 -> 0.055236648 | AC58: =E58*$K$17 -> -0.045427842 | AD58: =AB58-$K$13/12-AC58 -> 0.094538671 | AE58: 411.98 | AF58: =(AE57-AE58)/AE58 -> -0.037331909 | AG58: =AF58-$E$7/12 -> -0.040870243 | AH58: =E58*$L$17 -> -0.038573553 | AI58: =AG58-$L$13/12-AH58 -> -0.0059480441 | AJ58: 107.68 | AK58: =(AJ57-AJ58)/AJ58 -> 0.075501486 | AL58: =AK58-$E$7/12 -> 0.071963153 | AM58: =E58*$M$17 -> -0.033238232 | AN58: =AL58-$M$13/12-AM58 -> 0.10408298 | AO58: 98.16 | AP58: =(AO57-AO58)/AO58 -> 0.0045843521 | AQ58: =AP58-$E$7/12 -> 0.0010460187 | AR58: =E58*$N$17 -> -0.020846438 | AS58: =AQ58-$N$13/12-AR58 -> 0.016672432 | AT58: =AT59*(1+AU58) -> 189.91549 | AU58: =$F$32*E58+$G$32*H58+$H$32*M58+$I$32*R58+$J$32*W58+$K$32*AB58+$L$32*AG58+$M$32*AL58+$N$32*AQ58 -> -0.015353126 | AV58: 52.02 | AW58: =(AV57-AV58)/AV58 -> 0.006343714 | AX58: =AW58-$E$7/12 -> 0.0028053806 | AZ58: =E58-AX58 -> -0.048006238
B59: 45303 | C59: 96.14 | D59: =(C58-C59)/C59 -> 0.046078635 | E59: =D59-$E$7/12 -> 0.042540302 | F59: 219.39 | G59: =(F58-F59)/F59 -> 0.083367519 | H59: =G59-$E$7/12 -> 0.079829186 | I59: =$G$17*E59 -> 0.049407393 | J59: =H59-$G$13/12-I59 -> 0.016800953 | K59: 403.84 | L59: =(K58-K59)/K59 -> 0.0018819334 | M59: =L59-$E$7/12 -> -0.0016563999 | N59: =$H$17*E59 -> 0.075972185 | O59: =M59-$G$13/12-N59 -> -0.091249425 | P59: 916.27 | Q59: =(P58-P59)/P59 -> 0.069422768 | R59: =Q59-$E$7/12 -> 0.065884435 | S59: =E59*$I$17 -> 0.031477421 | T59: =R59-$I$13/12-S59 -> 0.024013809 | U59: 891.32 | V59: =(U58-U59)/U59 -> 0.095857829 | W59: =V59-$E$7/12 -> 0.092319496 | X59: =E59*$J$17 -> 0.048862584 | Y59: =W59-$J$13/12-X59 -> 0.02276091 | Z59: 4968.42 | AA59: =(Z58-Z59)/Z59 -> -0.046465476 | AB59: =AA59-$E$7/12 -> -0.050003809 | AC59: =E59*$K$17 -> 0.042753927 | AD59: =AB59-$K$13/12-AC59 -> -0.098883554 | AE59: 388.99 | AF59: =(AE58-AE59)/AE59 -> 0.059101776 | AG59: =AF59-$E$7/12 -> 0.055563443 | AH59: =E59*$L$17 -> 0.036303086 | AI59: =AG59-$L$13/12-AH59 -> 0.015609002 | AJ59: 91.25 | AK59: =(AJ58-AJ59)/AJ59 -> 0.18005479 | AL59: =AK59-$E$7/12 -> 0.17651646 | AM59: =E59*$M$17 -> 0.031281805 | AN59: =AL59-$M$13/12-AM59 -> 0.14411625 | AO59: 90.35 | AP59: =(AO58-AO59)/AO59 -> 0.086441616 | AQ59: =AP59-$E$7/12 -> 0.082903283 | AR59: =E59*$N$17 -> 0.019619402 | AS59: =AQ59-$N$13/12-AR59 -> 0.058063857 | AT59: =AT60*(1+AU59) -> 192.87675 | AU59: =$F$32*E59+$G$32*H59+$H$32*M59+$I$32*R59+$J$32*W59+$K$32*AB59+$L$32*AG59+$M$32*AL59+$N$32*AQ59 -> 0.058863147 | AV59: 51.7 | AW59: =(AV58-AV59)/AV59 -> 0.0061895551 | AX59: =AW59-$E$7/12 -> 0.0026512218 | AZ59: =E59-AX59 -> 0.03988908
B60: 45302 | C60: 97.69 | D60: =(C59-C60)/C60 -> -0.015866517 | E60: =D60-$E$7/12 -> -0.01940485 | F60: 207.89 | G60: =(F59-F60)/F60 -> 0.055317716 | H60: =G60-$E$7/12 -> 0.051779383 | I60: =$G$17*E60 -> -0.022537288 | J60: =H60-$G$13/12-I60 -> 0.060695832 | K60: 345.16 | L60: =(K59-K60)/K60 -> 0.17000811 | M60: =L60-$E$7/12 -> 0.16646978 | N60: =$H$17*E60 -> -0.034654875 | O60: =M60-$G$13/12-N60 -> 0.18750381 | P60: 971.88 | Q60: =(P59-P60)/P60 -> -0.057218998 | R60: =Q60-$E$7/12 -> -0.060757332 | S60: =E60*$I$17 -> -0.014358493 | T60: =R60-$I$13/12-S60 -> -0.056792044 | U60: 886.81 | V60: =(U59-U60)/U60 -> 0.0050856441 | W60: =V60-$E$7/12 -> 0.0015473107 | X60: =E60*$J$17 -> -0.022288773 | Y60: =W60-$J$13/12-X60 -> 0.0031400819 | Z60: 5201.98 | AA60: =(Z59-Z60)/Z60 -> -0.044898289 | AB60: =AA60-$E$7/12 -> -0.048436622 | AC60: =E60*$K$17 -> -0.019502295 | AD60: =AB60-$K$13/12-AC60 -> -0.035060145 | AE60: 429.13 | AF60: =(AE59-AE60)/AE60 -> -0.093538089 | AG60: =AF60-$E$7/12 -> -0.097076422 | AH60: =E60*$L$17 -> -0.016559731 | AI60: =AG60-$L$13/12-AH60 -> -0.084168046 | AJ60: 102.46 | AK60: =(AJ59-AJ60)/AJ60 -> -0.10940855 | AL60: =AK60-$E$7/12 -> -0.11294688 | AM60: =E60*$M$17 -> -0.014269263 | AN60: =AL60-$M$13/12-AM60 -> -0.099796027 | AO60: 92.5 | AP60: =(AO59-AO60)/AO60 -> -0.023243243 | AQ60: =AP60-$E$7/12 -> -0.026781577 | AR60: =E60*$N$17 -> -0.0089494321 | AS60: =AQ60-$N$13/12-AR60 -> -0.023052169 | AT60: =AT61*(1+AU60) -> 182.15456 | AU60: =$F$32*E60+$G$32*H60+$H$32*M60+$I$32*R60+$J$32*W60+$K$32*AB60+$L$32*AG60+$M$32*AL60+$N$32*AQ60 -> -0.0254249 | AV60: 52.15 | AW60: =(AV59-AV60)/AV60 -> -0.0086289549 | AX60: =AW60-$E$7/12 -> -0.012167288 | AZ60: =E60-AX60 -> -0.0072375616
B61: 45301 | C61: 87.23 | D61: =(C60-C61)/C61 -> 0.11991287 | E61: =D61-$E$7/12 -> 0.11637454 | F61: 186.4 | G61: =(F60-F61)/F61 -> 0.1152897 | H61: =G61-$E$7/12 -> 0.11175137 | I61: =$G$17*E61 -> 0.13516036 | J61: =H61-$G$13/12-I61 -> -0.037029837 | K61: 249.85 | L61: =(K60-K61)/K61 -> 0.38146888 | M61: =L61-$E$7/12 -> 0.37793055 | N61: =$H$17*E61 -> 0.20783182 | O61: =M61-$G$13/12-N61 -> 0.15647789 | P61: 874.18 | Q61: =(P60-P61)/P61 -> 0.11176188 | R61: =Q61-$E$7/12 -> 0.10822355 | S61: =E61*$I$17 -> 0.086110587 | T61: =R61-$I$13/12-S61 -> 0.011719754 | U61: 756.03 | V61: =(U60-U61)/U61 -> 0.17298255 | W61: =V61-$E$7/12 -> 0.16944422 | X61: =E61*$J$17 -> 0.13366997 | Y61: =W61-$J$13/12-X61 -> 0.015078251 | Z61: 4676.25 | AA61: =(Z60-Z61)/Z61 -> 0.11242555 | AB61: =AA61-$E$7/12 -> 0.10888722 | AC61: =E61*$K$17 -> 0.11695894 | AD61: =AB61-$K$13/12-AC61 -> -0.014197536 | AE61: 393.75 | AF61: =(AE60-AE61)/AE61 -> 0.089853968 | AG61: =AF61-$E$7/12 -> 0.086315635 | AH61: =E61*$L$17 -> 0.099311824 | AI61: =AG61-$L$13/12-AH61 -> -0.016647544 | AJ61: 97.7 | AK61: =(AJ60-AJ61)/AJ61 -> 0.048720573 | AL61: =AK61-$E$7/12 -> 0.04518224 | AM61: =E61*$M$17 -> 0.085575456 | AN61: =AL61-$M$13/12-AM61 -> -0.041511622 | AO61: 81.95 | AP61: =(AO60-AO61)/AO61 -> 0.12873703 | AQ61: =AP61-$E$7/12 -> 0.1251987 | AR61: =E61*$N$17 -> 0.05367143 | AS61: =AQ61-$N$13/12-AR61 -> 0.066307247 | AT61: =AT62*(1+AU61) -> 186.90664 | AU61: =$F$32*E61+$G$32*H61+$H$32*M61+$I$32*R61+$J$32*W61+$K$32*AB61+$L$32*AG61+$M$32*AL61+$N$32*AQ61 -> 0.11839958 | AV61: 52 | AW61: =(AV60-AV61)/AV61 -> 0.0028846154 | AX61: =AW61-$E$7/12 -> -0.00065371795 | AZ61: =E61-AX61 -> 0.11702826
B62: 45300 | C62: 87.94 | D62: =(C61-C62)/C62 -> -0.0080736866 | E62: =D62-$E$7/12 -> -0.01161202 | F62: 186.33 | G62: =(F61-F62)/F62 -> 0.00037567756 | H62: =G62-$E$7/12 -> -0.0031626558 | I62: =$G$17*E62 -> -0.013486497 | J62: =H62-$G$13/12-I62 -> -0.0032969987 | K62: 261.63 | L62: =(K61-K62)/K62 -> -0.045025418 | M62: =L62-$E$7/12 -> -0.048563751 | N62: =$H$17*E62 -> -0.020737759 | O62: =M62-$G$13/12-N62 -> -0.041446831 | P62: 886.52 | Q62: =(P61-P62)/P62 -> -0.013919596 | R62: =Q62-$E$7/12 -> -0.017457929 | S62: =E62*$I$17 -> -0.0085922389 | T62: =R62-$I$13/12-S62 -> -0.019258895 | U62: 709.27 | V62: =(U61-U62)/U62 -> 0.065926939 | W62: =V62-$E$7/12 -> 0.062388606 | X62: =E62*$J$17 -> -0.013337783 | Y62: =W62-$J$13/12-X62 -> 0.055030387 | Z62: 4212.12 | AA62: =(Z61-Z62)/Z62 -> 0.11018917 | AB62: =AA62-$E$7/12 -> 0.10665084 | AC62: =E62*$K$17 -> -0.011670332 | AD62: =AB62-$K$13/12-AC62 -> 0.11219535 | AE62: 405.2 | AF62: =(AE61-AE62)/AE62 -> -0.028257651 | AG62: =AF62-$E$7/12 -> -0.031795984 | AH62: =E62*$L$17 -> -0.0099094774 | AI62: =AG62-$L$13/12-AH62 -> -0.025537861 | AJ62: 97.49 | AK62: =(AJ61-AJ62)/AJ62 -> 0.0021540671 | AL62: =AK62-$E$7/12 -> -0.0013842662 | AM62: =E62*$M$17 -> -0.0085388427 | AN62: =AL62-$M$13/12-AM62 -> 0.0060361701 | AO62: 80.75 | AP62: =(AO61-AO62)/AO62 -> 0.014860681 | AQ62: =AP62-$E$7/12 -> 0.011322348 | AR62: =E62*$N$17 -> -0.0053554129 | AS62: =AQ62-$N$13/12-AR62 -> 0.011457736 | AT62: =AT63*(1+AU62) -> 167.11974 | AU62: =$F$32*E62+$G$32*H62+$H$32*M62+$I$32*R62+$J$32*W62+$K$32*AB62+$L$32*AG62+$M$32*AL62+$N$32*AQ62 -> 0.0098013948 | AV62: 52.66 | AW62: =(AV61-AV62)/AV62 -> -0.012533232 | AX62: =AW62-$E$7/12 -> -0.016071565 | AZ62: =E62-AX62 -> 0.0044595455
B63: 45299 | C63: 83.71 | D63: =(C62-C63)/C63 -> 0.050531597 | E63: =D63-$E$7/12 -> 0.046993264 | F63: 178.5 | G63: =(F62-F63)/F63 -> 0.043865546 | H63: =G63-$E$7/12 -> 0.040327213 | I63: =$G$17*E63 -> 0.054579177 | J63: =H63-$G$13/12-I63 -> -0.027872804 | K63: 214.11 | L63: =(K62-K63)/K63 -> 0.22194199 | M63: =L63-$E$7/12 -> 0.21840366 | N63: =$H$17*E63 -> 0.083924673 | O63: =M63-$G$13/12-N63 -> 0.12085815 | P63: 892.38 | Q63: =(P62-P63)/P63 -> -0.0065667092 | R63: =Q63-$E$7/12 -> -0.010105043 | S63: =E63*$I$17 -> 0.034772361 | T63: =R63-$I$13/12-S63 -> -0.055270609 | U63: 701.35 | V63: =(U62-U63)/U63 -> 0.011292507 | W63: =V63-$E$7/12 -> 0.007754174 | X63: =E63*$J$17 -> 0.053977339 | Y63: =W63-$J$13/12-X63 -> -0.066919167 | Z63: 3909.23 | AA63: =(Z62-Z63)/Z63 -> 0.077480731 | AB63: =AA63-$E$7/12 -> 0.073942398 | AC63: =E63*$K$17 -> 0.04722925 | AD63: =AB63-$K$13/12-AC63 -> 0.02058733 | AE63: 368.5 | AF63: =(AE62-AE63)/AE63 -> 0.099592944 | AG63: =AF63-$E$7/12 -> 0.096054611 | AH63: =E63*$L$17 -> 0.040103159 | AI63: =AG63-$L$13/12-AH63 -> 0.052300097 | AJ63: 94.57 | AK63: =(AJ62-AJ63)/AJ63 -> 0.030876599 | AL63: =AK63-$E$7/12 -> 0.027338266 | AM63: =E63*$M$17 -> 0.034556269 | AN63: =AL63-$M$13/12-AM63 -> -0.0083364098 | AO63: 77.23 | AP63: =(AO62-AO63)/AO63 -> 0.045578143 | AQ63: =AP63-$E$7/12 -> 0.04203981 | AR63: =E63*$N$17 -> 0.021673088 | AS63: =AQ63-$N$13/12-AR63 -> 0.015146697 | AT63: =AT64*(1+AU63) -> 165.49763 | AU63: =$F$32*E63+$G$32*H63+$H$32*M63+$I$32*R63+$J$32*W63+$K$32*AB63+$L$32*AG63+$M$32*AL63+$N$32*AQ63 -> 0.043537975 | AV63: 52.33 | AW63: =(AV62-AV63)/AV63 -> 0.0063061341 | AX63: =AW63-$E$7/12 -> 0.0027678008 | AZ63: =E63-AX63 -> 0.044225463
B64: 45298 | C64: 82.13 | D64: =(C63-C64)/C64 -> 0.019237794 | E64: =D64-$E$7/12 -> 0.01569946 | F64: 186.98 | G64: =(F63-F64)/F64 -> -0.045352444 | H64: =G64-$E$7/12 -> -0.048890777 | I64: =$G$17*E64 -> 0.018233754 | J64: =H64-$G$13/12-I64 -> -0.080745371 | K64: 232.07 | L64: =(K63-K64)/K64 -> -0.077390443 | M64: =L64-$E$7/12 -> -0.080928776 | N64: =$H$17*E64 -> 0.028037467 | O64: =M64-$G$13/12-N64 -> -0.12258708 | P64: 822 | Q64: =(P63-P64)/P64 -> 0.085620438 | R64: =Q64-$E$7/12 -> 0.082082105 | S64: =E64*$I$17 -> 0.011616714 | T64: =R64-$I$13/12-S64 -> 0.060072185 | U64: 628.35 | V64: =(U63-U64)/U64 -> 0.11617729 | W64: =V64-$E$7/12 -> 0.11263896 | X64: =E64*$J$17 -> 0.018032693 | Y64: =W64-$J$13/12-X64 -> 0.073910262 | Z64: 3715.01 | AA64: =(Z63-Z64)/Z64 -> 0.052279805 | AB64: =AA64-$E$7/12 -> 0.048741472 | AC64: =E64*$K$17 -> 0.015778298 | AD64: =AB64-$K$13/12-AC64 -> 0.026837355 | AE64: 368.16 | AF64: =(AE63-AE64)/AE64 -> 0.00092351152 | AG64: =AF64-$E$7/12 -> -0.0026148218 | AH64: =E64*$L$17 -> 0.013397622 | AI64: =AG64-$L$13/12-AH64 -> -0.019663798 | AJ64: 77.95 | AK64: =(AJ63-AJ64)/AJ64 -> 0.2132136 | AL64: =AK64-$E$7/12 -> 0.20967527 | AM64: =E64*$M$17 -> 0.011544522 | AN64: =AL64-$M$13/12-AM64 -> 0.19701234 | AO64: 68.64 | AP64: =(AO63-AO64)/AO64 -> 0.12514569 | AQ64: =AP64-$E$7/12 -> 0.12160735 | AR64: =E64*$N$17 -> 0.0072405226 | AS64: =AQ64-$N$13/12-AR64 -> 0.10914681 | AT64: =AT65*(1+AU64) -> 158.59282 | AU64: =$F$32*E64+$G$32*H64+$H$32*M64+$I$32*R64+$J$32*W64+$K$32*AB64+$L$32*AG64+$M$32*AL64+$N$32*AQ64 -> 0.041653489 | AV64: 51.87 | AW64: =(AV63-AV64)/AV64 -> 0.0088683247 | AX64: =AW64-$E$7/12 -> 0.0053299913 | AZ64: =E64-AX64 -> 0.010369469
B65: 45297 | C65: 81.28 | D65: =(C64-C65)/C65 -> 0.010457677 | E65: =D65-$E$7/12 -> 0.0069193438 | F65: 193.25 | G65: =(F64-F65)/F65 -> -0.032445019 | H65: =G65-$E$7/12 -> -0.035983353 | I65: =$G$17*E65 -> 0.0080363027 | J65: =H65-$G$13/12-I65 -> -0.057640495 | K65: 197.88 | L65: =(K64-K65)/K65 -> 0.17278148 | M65: =L65-$E$7/12 -> 0.16924315 | N65: =$H$17*E65 -> 0.012357168 | O65: =M65-$G$13/12-N65 -> 0.14326514 | P65: 849.99 | Q65: =(P64-P65)/P65 -> -0.032929799 | R65: =Q65-$E$7/12 -> -0.036468133 | S65: =E65*$I$17 -> 0.0051199236 | T65: =R65-$I$13/12-S65 -> -0.051981261 | U65: 674.88 | V65: =(U64-U65)/U65 -> -0.06894559 | W65: =V65-$E$7/12 -> -0.072483924 | X65: =E65*$J$17 -> 0.0079476874 | Y65: =W65-$J$13/12-X65 -> -0.10112761 | Z65: 3961.5 | AA65: =(Z64-Z65)/Z65 -> -0.062221381 | AB65: =AA65-$E$7/12 -> -0.065759714 | AC65: =E65*$K$17 -> 0.0069540907 | AD65: =AB65-$K$13/12-AC65 -> -0.078839623 | AE65: 344.24 | AF65: =(AE64-AE65)/AE65 -> 0.069486405 | AG65: =AF65-$E$7/12 -> 0.065948072 | AH65: =E65*$L$17 -> 0.0059048367 | AI65: =AG65-$L$13/12-AH65 -> 0.05639188 | AJ65: 77.85 | AK65: =(AJ64-AJ65)/AJ65 -> 0.0012845215 | AL65: =AK65-$E$7/12 -> -0.0022538118 | AM65: =E65*$M$17 -> 0.005088106 | AN65: =AL65-$M$13/12-AM65 -> -0.0084603243 | AO65: 67.71 | AP65: =(AO64-AO65)/AO65 -> 0.013735047 | AQ65: =AP65-$E$7/12 -> 0.010196713 | AR65: =E65*$N$17 -> 0.0031911712 | AS65: =AQ65-$N$13/12-AR65 -> 0.0017855176 | AT65: =AT66*(1+AU65) -> 152.25103 | AU65: =$F$32*E65+$G$32*H65+$H$32*M65+$I$32*R65+$J$32*W65+$K$32*AB65+$L$32*AG65+$M$32*AL65+$N$32*AQ65 -> -0.014970196 | AV65: 51.24 | AW65: =(AV64-AV65)/AV65 -> 0.012295082 | AX65: =AW65-$E$7/12 -> 0.0087567486 | AZ65: =E65-AX65 -> -0.0018374048
B66: 45296 | C66: 79.29 | D66: =(C65-C66)/C66 -> 0.025097742 | E66: =D66-$E$7/12 -> 0.021559409 | F66: 176.44 | G66: =(F65-F66)/F66 -> 0.095273181 | H66: =G66-$E$7/12 -> 0.091734847 | I66: =$G$17*E66 -> 0.025039648 | J66: =H66-$G$13/12-I66 -> 0.053074359 | K66: 178.08 | L66: =(K65-K66)/K66 -> 0.11118598 | M66: =L66-$E$7/12 -> 0.10764765 | N66: =$H$17*E66 -> 0.038502675 | O66: =M66-$G$13/12-N66 -> 0.055524136 | P66: 809.89 | Q66: =(P65-P66)/P66 -> 0.049512897 | R66: =Q66-$E$7/12 -> 0.045974563 | S66: =E66*$I$17 -> 0.015952745 | T66: =R66-$I$13/12-S66 -> 0.019628613 | U66: 641.62 | V66: =(U65-U66)/U66 -> 0.051837536 | W66: =V66-$E$7/12 -> 0.048299203 | X66: =E66*$J$17 -> 0.024763539 | Y66: =W66-$J$13/12-X66 -> 0.002839662 | Z66: 3776.35 | AA66: =(Z65-Z66)/Z66 -> 0.049028824 | AB66: =AA66-$E$7/12 -> 0.045490491 | AC66: =E66*$K$17 -> 0.021667674 | AD66: =AB66-$K$13/12-AC66 -> 0.017696998 | AE66: 334.87 | AF66: =(AE65-AE66)/AE66 -> 0.027981008 | AG66: =AF66-$E$7/12 -> 0.024442674 | AH66: =E66*$L$17 -> 0.018398391 | AI66: =AG66-$L$13/12-AH66 -> 0.0023929288 | AJ66: 80.22 | AK66: =(AJ65-AJ66)/AJ66 -> -0.029543755 | AL66: =AK66-$E$7/12 -> -0.033082088 | AM66: =E66*$M$17 -> 0.015853607 | AN66: =AL66-$M$13/12-AM66 -> -0.050054102 | AO66: 65.76 | AP66: =(AO65-AO66)/AO66 -> 0.029653285 | AQ66: =AP66-$E$7/12 -> 0.026114951 | AR66: =E66*$N$17 -> 0.0099431054 | AS66: =AQ66-$N$13/12-AR66 -> 0.010951822 | AT66: =AT67*(1+AU66) -> 154.5649 | AU66: =$F$32*E66+$G$32*H66+$H$32*M66+$I$32*R66+$J$32*W66+$K$32*AB66+$L$32*AG66+$M$32*AL66+$N$32*AQ66 -> 0.049994781 | AV66: 51.14 | AW66: =(AV65-AV66)/AV66 -> 0.0019554165 | AX66: =AW66-$E$7/12 -> -0.0015829168 | AZ66: =E66-AX66 -> 0.023142326
B67: 45295 | C67: 77.71 | D67: =(C66-C67)/C67 -> 0.020332004 | E67: =D67-$E$7/12 -> 0.01679367 | F67: 175 | G67: =(F66-F67)/F67 -> 0.0082285714 | H67: =G67-$E$7/12 -> 0.0046902381 | I67: =$G$17*E67 -> 0.019504598 | J67: =H67-$G$13/12-I67 -> -0.028435199 | K67: 183.28 | L67: =(K66-K67)/K67 -> -0.02837189 | M67: =L67-$E$7/12 -> -0.031910223 | N67: =$H$17*E67 -> 0.029991603 | O67: =M67-$G$13/12-N67 -> -0.075522665 | P67: 722.9 | Q67: =(P66-P67)/P67 -> 0.12033476 | R67: =Q67-$E$7/12 -> 0.11679643 | S67: =E67*$I$17 -> 0.012426367 | T67: =R67-$I$13/12-S67 -> 0.093976857 | U67: 550.64 | V67: =(U66-U67)/U67 -> 0.16522592 | W67: =V67-$E$7/12 -> 0.16168759 | X67: =E67*$J$17 -> 0.019289523 | Y67: =W67-$J$13/12-X67 -> 0.12170206 | Z67: 3452.03 | AA67: =(Z66-Z67)/Z67 -> 0.093950516 | AB67: =AA67-$E$7/12 -> 0.090412183 | AC67: =E67*$K$17 -> 0.016878003 | AD67: =AB67-$K$13/12-AC67 -> 0.067408361 | AE67: 334.22 | AF67: =(AE66-AE67)/AE67 -> 0.0019448268 | AG67: =AF67-$E$7/12 -> -0.0015935066 | AH67: =E67*$L$17 -> 0.014331399 | AI67: =AG67-$L$13/12-AH67 -> -0.019576261 | AJ67: 88.49 | AK67: =(AJ66-AJ67)/AJ67 -> -0.093456888 | AL67: =AK67-$E$7/12 -> -0.096995221 | AM67: =E67*$M$17 -> 0.012349144 | AN67: =AL67-$M$13/12-AM67 -> -0.11046277 | AO67: 59.35 | AP67: =(AO66-AO67)/AO67 -> 0.10800337 | AQ67: =AP67-$E$7/12 -> 0.10446504 | AR67: =E67*$N$17 -> 0.0077451674 | AS67: =AQ67-$N$13/12-AR67 -> 0.091499845 | AT67: =AT68*(1+AU67) -> 147.2054 | AU67: =$F$32*E67+$G$32*H67+$H$32*M67+$I$32*R67+$J$32*W67+$K$32*AB67+$L$32*AG67+$M$32*AL67+$N$32*AQ67 -> 0.064469656 | AV67: 50.79 | AW67: =(AV66-AV67)/AV67 -> 0.0068911203 | AX67: =AW67-$E$7/12 -> 0.003352787 | AZ67: =E67-AX67 -> 0.013440883
B68: 45294 | C68: 81.97 | D68: =(C67-C68)/C68 -> -0.051970233 | E68: =D68-$E$7/12 -> -0.055508566 | F68: 180.38 | G68: =(F67-F68)/F68 -> -0.029825923 | H68: =G68-$E$7/12 -> -0.033364256 | I68: =$G$17*E68 -> -0.064469067 | J68: =H68-$G$13/12-I68 -> 0.017483971 | K68: 175.79 | L68: =(K67-K68)/K68 -> 0.042607657 | M68: =L68-$E$7/12 -> 0.039069324 | N68: =$H$17*E68 -> -0.099132044 | O68: =M68-$G$13/12-N68 -> 0.12458053 | P68: 732.63 | Q68: =(P67-P68)/P68 -> -0.013280919 | R68: =Q68-$E$7/12 -> -0.016819253 | S68: =E68*$I$17 -> -0.041073204 | T68: =R68-$I$13/12-S68 -> 0.013860746 | U68: 607.33 | V68: =(U67-U68)/U68 -> -0.093342993 | W68: =V68-$E$7/12 -> -0.096881326 | X68: =E68*$J$17 -> -0.063758175 | Y68: =W68-$J$13/12-X68 -> -0.053819153 | Z68: 3627.88 | AA68: =(Z67-Z68)/Z68 -> -0.048471835 | AB68: =AA68-$E$7/12 -> -0.052010168 | AC68: =E68*$K$17 -> -0.055787314 | AD68: =AB68-$K$13/12-AC68 -> -0.0023486729 | AE68: 383.6 | AF68: =(AE67-AE68)/AE68 -> -0.12872784 | AG68: =AF68-$E$7/12 -> -0.13226617 | AH68: =E68*$L$17 -> -0.047369957 | AI68: =AG68-$L$13/12-AH68 -> -0.088547573 | AJ68: 91.39 | AK68: =(AJ67-AJ68)/AJ68 -> -0.031732137 | AL68: =AK68-$E$7/12 -> -0.03527047 | AM68: =E68*$M$17 -> -0.040817956 | AN68: =AL68-$M$13/12-AM68 -> 0.0044290792 | AO68: 60.17 | AP68: =(AO67-AO68)/AO68 -> -0.013628054 | AQ68: =AP68-$E$7/12 -> -0.017166387 | AR68: =E68*$N$17 -> -0.025600309 | AS68: =AQ68-$N$13/12-AR68 -> 0.003213897 | AT68: =AT69*(1+AU68) -> 138.2899 | AU68: =$F$32*E68+$G$32*H68+$H$32*M68+$I$32*R68+$J$32*W68+$K$32*AB68+$L$32*AG68+$M$32*AL68+$N$32*AQ68 -> -0.051506025 | AV68: 51.28 | AW68: =(AV67-AV68)/AV68 -> -0.0095553822 | AX68: =AW68-$E$7/12 -> -0.013093716 | AZ68: =E68-AX68 -> -0.042414851
B69: 45293 | C69: 80.91 | D69: =(C68-C69)/C69 -> 0.013100976 | E69: =D69-$E$7/12 -> 0.0095626431 | F69: 176.76 | G69: =(F68-F69)/F69 -> 0.020479747 | H69: =G69-$E$7/12 -> 0.016941413 | I69: =$G$17*E69 -> 0.011106298 | J69: =H69-$G$13/12-I69 -> -0.0077857242 | K69: 201.88 | L69: =(K68-K69)/K69 -> -0.12923519 | M69: =L69-$E$7/12 -> -0.13277352 | N69: =$H$17*E69 -> 0.017077803 | O69: =M69-$G$13/12-N69 -> -0.16347216 | P69: 743.89 | Q69: =(P68-P69)/P69 -> -0.015136647 | R69: =Q69-$E$7/12 -> -0.01867498 | S69: =E69*$I$17 -> 0.0070758158 | T69: =R69-$I$13/12-S69 -> -0.036144001 | U69: 602.92 | V69: =(U68-U69)/U69 -> 0.0073144032 | W69: =V69-$E$7/12 -> 0.0037760699 | X69: =E69*$J$17 -> 0.01098383 | Y69: =W69-$J$13/12-X69 -> -0.027903762 | Z69: 3468.83 | AA69: =(Z68-Z69)/Z69 -> 0.045851195 | AB69: =AA69-$E$7/12 -> 0.042312861 | AC69: =E69*$K$17 -> 0.0096106638 | AD69: =AB69-$K$13/12-AC69 -> 0.026576379 | AE69: 380.61 | AF69: =(AE68-AE69)/AE69 -> 0.0078558104 | AG69: =AF69-$E$7/12 -> 0.0043174771 | AH69: =E69*$L$17 -> 0.0081605781 | AI69: =AG69-$L$13/12-AH69 -> -0.0074944559 | AJ69: 94.9 | AK69: =(AJ68-AJ69)/AJ69 -> -0.036986301 | AL69: =AK69-$E$7/12 -> -0.040524635 | AM69: =E69*$M$17 -> 0.0070318433 | AN69: =AL69-$M$13/12-AM69 -> -0.048674884 | AO69: 58.61 | AP69: =(AO68-AO69)/AO69 -> 0.026616618 | AQ69: =AP69-$E$7/12 -> 0.023078285 | AR69: =E69*$N$17 -> 0.0044102492 | AS69: =AQ69-$N$13/12-AR69 -> 0.013448011 | AT69: =AT70*(1+AU69) -> 145.79945 | AU69: =$F$32*E69+$G$32*H69+$H$32*M69+$I$32*R69+$J$32*W69+$K$32*AB69+$L$32*AG69+$M$32*AL69+$N$32*AQ69 -> 0.0056843676 | AV69: 51.07 | AW69: =(AV68-AV69)/AV69 -> 0.0041120031 | AX69: =AW69-$E$7/12 -> 0.0005736698 | AZ69: =E69-AX69 -> 0.0089889733
... B115: 43834 | C115: 51.19 | D115: =(C114-C115)/C115 -> 0.063488963 | E115: =D115-$E$7/12 -> 0.059950629 | F115: 123.7 | G115: =(F114-F115)/F115 -> -0.012772838 | H115: =G115-$E$7/12 -> -0.016311171 | I115: =$G$17*E115 -> 0.069628192 | J115: =H115-$G$13/12-I115 -> -0.099560203 | K115: 52.13 | L115: =(K114-K115)/K115 -> 0.067907155 | M115: =L115-$E$7/12 -> 0.064368822 | N115: =$H$17*E115 -> 0.10706507 | O115: =M115-$G$13/12-N115 -> -0.056317086 | P115: 288.7 | Q115: =(P114-P115)/P115 -> 0.018046415 | R115: =Q115-$E$7/12 -> 0.014508082 | S115: =E115*$I$17 -> 0.04436008 | T115: =R115-$I$13/12-S115 -> -0.040245203 | U115: 419.85 | V115: =(U114-U115)/U115 -> -0.00028581636 | W115: =V115-$E$7/12 -> -0.0038241497 | X115: =E115*$J$17 -> 0.068860411 | Y115: =W115-$J$13/12-X115 -> -0.093380562 | Z115: 1480.57 | AA115: =(Z114-Z115)/Z115 -> 0.10728976 | AB115: =AA115-$E$7/12 -> 0.10375143 | AC115: =E115*$K$17 -> 0.060251683 | AD115: =AB115-$K$13/12-AC115 -> 0.037373925 | AE115: 219.83 | AF115: =(AE114-AE115)/AE115 -> 0.13032798 | AG115: =AF115-$E$7/12 -> 0.12678965 | AH115: =E115*$L$17 -> 0.051160729 | AI115: =AG115-$L$13/12-AH115 -> 0.071977563 | AJ115: 76.73 | AK115: =(AJ114-AJ115)/AJ115 -> 0.016421217 | AL115: =AK115-$E$7/12 -> 0.012882884 | AM115: =E115*$M$17 -> 0.044084405 | AN115: =AL115-$M$13/12-AM115 -> -0.032319928 | AO115: 40.52 | AP115: =(AO114-AO115)/AO115 -> 0.020483712 | AQ115: =AP115-$E$7/12 -> 0.016945378 | AR115: =E115*$N$17 -> 0.027648969 | AS115: =AQ115-$N$13/12-AR115 -> -0.015923615 | AT115: =AT116*(1+AU115) -> 88.097528 | AU115: =$F$32*E115+$G$32*H115+$H$32*M115+$I$32*R115+$J$32*W115+$K$32*AB115+$L$32*AG115+$M$32*AL115+$N$32*AQ115 -> 0.036754575 | AV115: 53.67 | AW115: =(AV114-AV115)/AV115 -> 0.013042668 | AX115: =AW115-$E$7/12 -> 0.0095043348 | AZ115: =E115-AX115 -> 0.050446295
B116: 43833 | C116: 44.29 | D116: =(C115-C116)/C116 -> 0.15579138 | E116: =D116-$E$7/12 -> 0.15225304 | F116: 97.49 | G116: =(F115-F116)/F116 -> 0.26884809 | H116: =G116-$E$7/12 -> 0.26530975 | I116: =$G$17*E116 -> 0.17683057 | J116: =H116-$G$13/12-I116 -> 0.074858342 | K116: 34.93 | L116: =(K115-K116)/K116 -> 0.4924134 | M116: =L116-$E$7/12 -> 0.48887506 | N116: =$H$17*E116 -> 0.27190677 | O116: =M116-$G$13/12-N116 -> 0.20334745 | P116: 271.67 | Q116: =(P115-P116)/P116 -> 0.062686347 | R116: =Q116-$E$7/12 -> 0.059148014 | S116: =E116*$I$17 -> 0.11265865 | T116: =R116-$I$13/12-S116 -> -0.063903843 | U116: 375.5 | V116: =(U115-U116)/U116 -> 0.11810919 | W116: =V116-$E$7/12 -> 0.11457085 | X116: =E116*$J$17 -> 0.17488068 | Y116: =W116-$J$13/12-X116 -> -0.081005831 | Z116: 1345.32 | AA116: =(Z115-Z116)/Z116 -> 0.1005337 | AB116: =AA116-$E$7/12 -> 0.096995369 | AC116: =E116*$K$17 -> 0.15301761 | AD116: =AB116-$K$13/12-AC116 -> -0.062148061 | AE116: 186.71 | AF116: =(AE115-AE116)/AE116 -> 0.17738739 | AG116: =AF116-$E$7/12 -> 0.17384906 | AH116: =E116*$L$17 -> 0.12992986 | AI116: =AG116-$L$13/12-AH116 -> 0.040267848 | AJ116: 65.74 | AK116: =(AJ115-AJ116)/AJ116 -> 0.16717371 | AL116: =AK116-$E$7/12 -> 0.16363538 | AM116: =E116*$M$17 -> 0.11195854 | AN116: =AL116-$M$13/12-AM116 -> 0.050558437 | AO116: 37.87 | AP116: =(AO115-AO116)/AO116 -> 0.069976234 | AQ116: =AP116-$E$7/12 -> 0.066437901 | AR116: =E116*$N$17 -> 0.070218438 | AS116: =AQ116-$N$13/12-AR116 -> -0.0090005615 | AT116: =AT117*(1+AU116) -> 84.974333 | AU116: =$F$32*E116+$G$32*H116+$H$32*M116+$I$32*R116+$J$32*W116+$K$32*AB116+$L$32*AG116+$M$32*AL116+$N$32*AQ116 -> 0.1467141 | AV116: 52.36 | AW116: =(AV115-AV116)/AV116 -> 0.025019099 | AX116: =AW116-$E$7/12 -> 0.021480765 | AZ116: =E116-AX116 -> 0.13077228 | BA116: Tracking Error
B117: 43832 | C117: 52.1 | D117: =(C116-C117)/C117 -> -0.14990403 | E117: =D117-$E$7/12 -> -0.15344236 | F117: 94.19 | G117: =(F116-F117)/F117 -> 0.035035566 | H117: =G117-$E$7/12 -> 0.031497233 | I117: =$G$17*E117 -> -0.17821188 | J117: =H117-$G$13/12-I117 -> 0.19608827 | K117: 44.53 | L117: =(K116-K117)/K117 -> -0.215585 | M117: =L117-$E$7/12 -> -0.21912333 | N117: =$H$17*E117 -> -0.27403077 | O117: =M117-$G$13/12-N117 -> 0.041286599 | P117: 267.87 | Q117: =(P116-P117)/P117 -> 0.014185986 | R117: =Q117-$E$7/12 -> 0.010647652 | S117: =E117*$I$17 -> -0.11353868 | T117: =R117-$I$13/12-S117 -> 0.11379313 | U117: 369.03 | V117: =(U116-U117)/U117 -> 0.01753245 | W117: =V117-$E$7/12 -> 0.013994117 | X117: =E117*$J$17 -> -0.17624676 | Y117: =W117-$J$13/12-X117 -> 0.16954488 | Z117: 1695.66 | AA117: =(Z116-Z117)/Z117 -> -0.20660982 | AB117: =AA117-$E$7/12 -> -0.21014815 | AC117: =E117*$K$17 -> -0.15421291 | AD117: =AB117-$K$13/12-AC117 -> -0.062061062 | AE117: 217.84 | AF117: =(AE116-AE117)/AE117 -> -0.14290305 | AG117: =AF117-$E$7/12 -> -0.14644138 | AH117: =E117*$L$17 -> -0.1309448 | AI117: =AG117-$L$13/12-AH117 -> -0.019147935 | AJ117: 78.43 | AK117: =(AJ116-AJ117)/AJ117 -> -0.16180033 | AL117: =AK117-$E$7/12 -> -0.16533866 | AM117: =E117*$M$17 -> -0.1128331 | AN117: =AL117-$M$13/12-AM117 -> -0.053623971 | AO117: 35.89 | AP117: =(AO116-AO117)/AO117 -> 0.055168571 | AQ117: =AP117-$E$7/12 -> 0.051630237 | AR117: =E117*$N$17 -> -0.070766949 | AS117: =AQ117-$N$13/12-AR117 -> 0.11717716 | AT117: =AT118*(1+AU117) -> 74.102457 | AU117: =$F$32*E117+$G$32*H117+$H$32*M117+$I$32*R117+$J$32*W117+$K$32*AB117+$L$32*AG117+$M$32*AL117+$N$32*AQ117 -> -0.039668269 | AV117: 54.39 | AW117: =(AV116-AV117)/AV117 -> -0.037323037 | AX117: =AW117-$E$7/12 -> -0.040861371 | AZ117: =E117-AX117 -> -0.11258099 | BA117: SD of TE
B118: 43831 | C118: 56.6 | D118: =(C117-C118)/C118 -> -0.0795053 | E118: =D118-$E$7/12 -> -0.083043634 | F118: 100.44 | G118: =(F117-F118)/F118 -> -0.062226205 | H118: =G118-$E$7/12 -> -0.065764538 | I118: =$G$17*E118 -> -0.096448997 | J118: =H118-$G$13/12-I118 -> 0.01706362 | K118: 43.37 | L118: =(K117-K118)/K118 -> 0.026746599 | M118: =L118-$E$7/12 -> 0.023208266 | N118: =$H$17*E118 -> -0.14830657 | O118: =M118-$G$13/12-N118 -> 0.157894 | P118: 291.1 | Q118: =(P117-P118)/P118 -> -0.079800756 | R118: =Q118-$E$7/12 -> -0.083339089 | S118: =E118*$I$17 -> -0.061447599 | T118: =R118-$I$13/12-S118 -> -0.032284696 | U118: 345.09 | V118: =(U117-U118)/U118 -> 0.069373207 | W118: =V118-$E$7/12 -> 0.065834874 | X118: =E118*$J$17 -> -0.095385467 | Y118: =W118-$J$13/12-X118 -> 0.14052434 | Z118: 1830.55 | AA118: =(Z117-Z118)/Z118 -> -0.073688236 | AB118: =AA118-$E$7/12 -> -0.077226569 | AC118: =E118*$K$17 -> -0.083460654 | AD118: =AB118-$K$13/12-AC118 -> 0.00010826627 | AE118: 228.1 | AF118: =(AE117-AE118)/AE118 -> -0.044980272 | AG118: =AF118-$E$7/12 -> -0.048518605 | AH118: =E118*$L$17 -> -0.070867861 | AI118: =AG118-$L$13/12-AH118 -> 0.018697901 | AJ118: 84.83 | AK118: =(AJ117-AJ118)/AJ118 -> -0.075445008 | AL118: =AK118-$E$7/12 -> -0.078983341 | AM118: =E118*$M$17 -> -0.061065735 | AN118: =AL118-$M$13/12-AM118 -> -0.019036013 | AO118: 38.16 | AP118: =(AO117-AO118)/AO118 -> -0.059486373 | AQ118: =AP118-$E$7/12 -> -0.063024706 | AR118: =E118*$N$17 -> -0.038299361 | AS118: =AQ118-$N$13/12-AR118 -> -0.029945369 | AT118: =AT119*(1+AU118) -> 77.163396 | AU118: =$F$32*E118+$G$32*H118+$H$32*M118+$I$32*R118+$J$32*W118+$K$32*AB118+$L$32*AG118+$M$32*AL118+$N$32*AQ118 -> -0.052704037 | AV118: 54.11 | AW118: =(AV117-AV118)/AV118 -> 0.0051746442 | AX118: =AW118-$E$7/12 -> 0.0016363109 | AZ118: =E118-AX118 -> -0.084679945 | BA118: Correlation
B119: 43477 | C119: 57.06 | D119: =(C118-C119)/C119 -> -0.0080616894 | E119: =D119-$E$7/12 -> -0.011600023 | F119: 92.39 | G119: =(F118-F119)/F119 -> 0.087130642 | H119: =G119-$E$7/12 -> 0.083592309 | I119: =$G$17*E119 -> -0.013472563 | J119: =H119-$G$13/12-I119 -> 0.083444032 | K119: 27.89 | L119: =(K118-K119)/K119 -> 0.55503765 | M119: =L119-$E$7/12 -> 0.55149931 | N119: =$H$17*E119 -> -0.020716333 | O119: =M119-$G$13/12-N119 -> 0.55859481 | P119: 280.05 | Q119: =(P118-P119)/P119 -> 0.03945724 | R119: =Q119-$E$7/12 -> 0.035918906 | S119: =E119*$I$17 -> -0.0085833617 | T119: =R119-$I$13/12-S119 -> 0.034109063 | U119: 323.57 | V119: =(U118-U119)/U119 -> 0.06650802 | W119: =V119-$E$7/12 -> 0.062969687 | X119: =E119*$J$17 -> -0.013324003 | Y119: =W119-$J$13/12-X119 -> 0.055597688 | Z119: 2053.73 | AA119: =(Z118-Z119)/Z119 -> -0.10867057 | AB119: =AA119-$E$7/12 -> -0.1122089 | AC119: =E119*$K$17 -> -0.011658275 | AD119: =AB119-$K$13/12-AC119 -> -0.10667644 | AE119: 218.38 | AF119: =(AE118-AE119)/AE119 -> 0.04450957 | AG119: =AF119-$E$7/12 -> 0.040971237 | AH119: =E119*$L$17 -> -0.0098992393 | AI119: =AG119-$L$13/12-AH119 -> 0.047219122 | AJ119: 87.92 | AK119: =(AJ118-AJ119)/AJ119 -> -0.035145587 | AL119: =AK119-$E$7/12 -> -0.03868392 | AM119: =E119*$M$17 -> -0.0085300207 | AN119: =AL119-$M$13/12-AM119 -> -0.031272306 | AO119: 39.61 | AP119: =(AO118-AO119)/AO119 -> -0.036606917 | AQ119: =AP119-$E$7/12 -> -0.040145251 | AR119: =E119*$N$17 -> -0.0053498799 | AS119: =AQ119-$N$13/12-AR119 -> -0.040015395 | AT119: =AT120*(1+AU119) -> 81.456481 | AU119: =$F$32*E119+$G$32*H119+$H$32*M119+$I$32*R119+$J$32*W119+$K$32*AB119+$L$32*AG119+$M$32*AL119+$N$32*AQ119 -> 0.031559739 | AV119: 53.63 | AW119: =(AV118-AV119)/AV119 -> 0.0089502144 | AX119: =AW119-$E$7/12 -> 0.0054118811 | AZ119: =E119-AX119 -> -0.017011904 | BA119: R^2
B120: 43476 | C120: 56.39 | D120: =(C119-C120)/C120 -> 0.011881539 | E120: =D120-$E$7/12 -> 0.0083432059 | F120: 90.04 | G120: =(F119-F120)/F120 -> 0.026099511 | H120: =G120-$E$7/12 -> 0.022561178 | I120: =$G$17*E120 -> 0.0096900125 | J120: =H120-$G$13/12-I120 -> -0.00074967399 | K120: 22 | L120: =(K119-K120)/K120 -> 0.26772727 | M120: =L120-$E$7/12 -> 0.26418894 | N120: =$H$17*E120 -> 0.014900026 | O120: =M120-$G$13/12-N120 -> 0.23566807 | P120: 285.66 | Q120: =(P119-P120)/P120 -> -0.019638731 | R120: =Q120-$E$7/12 -> -0.023177065 | S120: =E120*$I$17 -> 0.0061735012 | T120: =R120-$I$13/12-S120 -> -0.039743771 | U120: 314.66 | V120: =(U119-U120)/U120 -> 0.028316278 | W120: =V120-$E$7/12 -> 0.024777945 | X120: =E120*$J$17 -> 0.009583162 | Y120: =W120-$J$13/12-X120 -> -0.0055012188 | Z120: 1904.03 | AA120: =(Z119-Z120)/Z120 -> 0.078622711 | AB120: =AA120-$E$7/12 -> 0.075084377 | AC120: =E120*$K$17 -> 0.008385103 | AD120: =AB120-$K$13/12-AC120 -> 0.060573456 | AE120: 220.51 | AF120: =(AE119-AE120)/AE120 -> -0.0096594259 | AG120: =AF120-$E$7/12 -> -0.013197759 | AH120: =E120*$L$17 -> 0.0071199336 | AI120: =AG120-$L$13/12-AH120 -> -0.023969048 | AJ120: 85.43 | AK120: =(AJ119-AJ120)/AJ120 -> 0.02914667 | AL120: =AK120-$E$7/12 -> 0.025608336 | AM120: =E120*$M$17 -> 0.0061351362 | AN120: =AL120-$M$13/12-AM120 -> 0.018354794 | AO120: 39.7 | AP120: =(AO119-AO120)/AO120 -> -0.0022670025 | AQ120: =AP120-$E$7/12 -> -0.0058053359 | AR120: =E120*$N$17 -> 0.0038478502 | AS120: =AQ120-$N$13/12-AR120 -> -0.01487321 | AT120: =AT121*(1+AU120) -> 78.964386 | AU120: =$F$32*E120+$G$32*H120+$H$32*M120+$I$32*R120+$J$32*W120+$K$32*AB120+$L$32*AG120+$M$32*AL120+$N$32*AQ120 -> 0.014615029 | AV120: 53.69 | AW120: =(AV119-AV120)/AV120 -> -0.0011175265 | AX120: =AW120-$E$7/12 -> -0.0046558599 | AZ120: =E120-AX120 -> 0.012999066 | BA120: Slope (B)
B121: 43475 | C121: 54.96 | D121: =(C120-C121)/C121 -> 0.026018923 | E121: =D121-$E$7/12 -> 0.02248059 | F121: 88.83 | G121: =(F120-F121)/F121 -> 0.013621524 | H121: =G121-$E$7/12 -> 0.010083191 | I121: =$G$17*E121 -> 0.026109531 | J121: =H121-$G$13/12-I121 -> -0.029647179 | K121: 20.99 | L121: =(K120-K121)/K121 -> 0.048118152 | M121: =L121-$E$7/12 -> 0.044579818 | N121: =$H$17*E121 -> 0.040147799 | O121: =M121-$G$13/12-N121 -> -0.0091888208 | P121: 283.09 | Q121: =(P120-P121)/P121 -> 0.009078385 | R121: =Q121-$E$7/12 -> 0.0055400516 | S121: =E121*$I$17 -> 0.016634367 | T121: =R121-$I$13/12-S121 -> -0.02148752 | U121: 287.41 | V121: =(U120-U121)/U121 -> 0.094812289 | W121: =V121-$E$7/12 -> 0.091273956 | X121: =E121*$J$17 -> 0.025821624 | Y121: =W121-$J$13/12-X121 -> 0.04475633 | Z121: 2048.77 | AA121: =(Z120-Z121)/Z121 -> -0.070647266 | AB121: =AA121-$E$7/12 -> -0.0741856 | AC121: =E121*$K$17 -> 0.02259348 | AD121: =AB121-$K$13/12-AC121 -> -0.1029049 | AE121: 234.58 | AF121: =(AE120-AE121)/AE121 -> -0.059979538 | AG121: =AF121-$E$7/12 -> -0.063517871 | AH121: =E121*$L$17 -> 0.019184508 | AI121: =AG121-$L$13/12-AH121 -> -0.086353735 | AJ121: 84.56 | AK121: =(AJ120-AJ121)/AJ121 -> 0.010288553 | AL121: =AK121-$E$7/12 -> 0.0067502192 | AM121: =E121*$M$17 -> 0.016530993 | AN121: =AL121-$M$13/12-AM121 -> -0.01089918 | AO121: 39.09 | AP121: =(AO120-AO121)/AO121 -> 0.015605014 | AQ121: =AP121-$E$7/12 -> 0.012066681 | AR121: =E121*$N$17 -> 0.01036795 | AS121: =AQ121-$N$13/12-AR121 -> -0.0035212934 | AT121: =AT122*(1+AU121) -> 77.826943 | AU121: =$F$32*E121+$G$32*H121+$H$32*M121+$I$32*R121+$J$32*W121+$K$32*AB121+$L$32*AG121+$M$32*AL121+$N$32*AQ121 -> -0.0043124744 | AV121: 53.78 | AW121: =(AV120-AV121)/AV121 -> -0.0016734846 | AX121: =AW121-$E$7/12 -> -0.0052118179 | AZ121: =E121-AX121 -> 0.027692407
B122: 43474 | C122: 54.35 | D122: =(C121-C122)/C122 -> 0.011223551 | E122: =D122-$E$7/12 -> 0.0076852177 | F122: 86.8 | G122: =(F121-F122)/F122 -> 0.023387097 | H122: =G122-$E$7/12 -> 0.019848763 | I122: =$G$17*E122 -> 0.0089258082 | J122: =H122-$G$13/12-I122 -> -0.0026978842 | K122: 16.06 | L122: =(K121-K122)/K122 -> 0.30697385 | M122: =L122-$E$7/12 -> 0.30343551 | N122: =$H$17*E122 -> 0.013724933 | O122: =M122-$G$13/12-N122 -> 0.27608974 | P122: 274.51 | Q122: =(P121-P122)/P122 -> 0.031255692 | R122: =Q122-$E$7/12 -> 0.027717359 | S122: =E122*$I$17 -> 0.0056866271 | T122: =R122-$I$13/12-S122 -> 0.011637526 | U122: 267.62 | V122: =(U121-U122)/U122 -> 0.073948135 | W122: =V122-$E$7/12 -> 0.070409802 | X122: =E122*$J$17 -> 0.0088273844 | Y122: =W122-$J$13/12-X122 -> 0.040886416 | Z122: 1962.61 | AA122: =(Z121-Z122)/Z122 -> 0.043900724 | AB122: =AA122-$E$7/12 -> 0.040362391 | AC122: =E122*$K$17 -> 0.0077238106 | AD122: =AB122-$K$13/12-AC122 -> 0.026512762 | AE122: 232.02 | AF122: =(AE121-AE122)/AE122 -> 0.011033532 | AG122: =AF122-$E$7/12 -> 0.0074951983 | AH122: =E122*$L$17 -> 0.0065584189 | AI122: =AG122-$L$13/12-AH122 -> -0.0027145755 | AJ122: 88.42 | AK122: =(AJ121-AJ122)/AJ122 -> -0.043655282 | AL122: =AK122-$E$7/12 -> -0.047193615 | AM122: =E122*$M$17 -> 0.0056512877 | AN122: =AL122-$M$13/12-AM122 -> -0.053963309 | AO122: 39.56 | AP122: =(AO121-AO122)/AO122 -> -0.011880688 | AQ122: =AP122-$E$7/12 -> -0.015419021 | AR122: =E122*$N$17 -> 0.0035443889 | AS122: =AQ122-$N$13/12-AR122 -> -0.024183434 | AT122: =AT123*(1+AU122) -> 78.164023 | AU122: =$F$32*E122+$G$32*H122+$H$32*M122+$I$32*R122+$J$32*W122+$K$32*AB122+$L$32*AG122+$M$32*AL122+$N$32*AQ122 -> 0.026944189 | AV122: 53.67 | AW122: =(AV121-AV122)/AV122 -> 0.0020495621 | AX122: =AW122-$E$7/12 -> -0.0014887712 | AZ122: =E122-AX122 -> 0.0091739889
B123: 43473 | C123: 54.65 | D123: =(C122-C123)/C123 -> -0.0054894785 | E123: =D123-$E$7/12 -> -0.0090278118 | F123: 88.81 | G123: =(F122-F123)/F123 -> -0.022632586 | H123: =G123-$E$7/12 -> -0.02617092 | I123: =$G$17*E123 -> -0.010485131 | J123: =H123-$G$13/12-I123 -> -0.029306628 | K123: 15.04 | L123: =(K122-K123)/K123 -> 0.067819149 | M123: =L123-$E$7/12 -> 0.064280816 | N123: =$H$17*E123 -> -0.016122655 | O123: =M123-$G$13/12-N123 -> 0.066782631 | P123: 280.85 | Q123: =(P122-P123)/P123 -> -0.022574328 | R123: =Q123-$E$7/12 -> -0.026112661 | S123: =E123*$I$17 -> -0.0066800709 | T123: =R123-$I$13/12-S123 -> -0.029825796 | U123: 293.75 | V123: =(U122-U123)/U123 -> -0.088953191 | W123: =V123-$E$7/12 -> -0.092491525 | X123: =E123*$J$17 -> -0.010369513 | Y123: =W123-$J$13/12-X123 -> -0.10281801 | Z123: 1966.41 | AA123: =(Z122-Z123)/Z123 -> -0.0019324556 | AB123: =AA123-$E$7/12 -> -0.0054707889 | AC123: =E123*$K$17 -> -0.0090731468 | AD123: =AB123-$K$13/12-AC123 -> -0.0025234606 | AE123: 227.91 | AF123: =(AE122-AE123)/AE123 -> 0.018033434 | AG123: =AF123-$E$7/12 -> 0.014495101 | AH123: =E123*$L$17 -> -0.0077041633 | AI123: =AG123-$L$13/12-AH123 -> 0.018547909 | AJ123: 96.56 | AK123: =(AJ122-AJ123)/AJ123 -> -0.084299917 | AL123: =AK123-$E$7/12 -> -0.08783825 | AM123: =E123*$M$17 -> -0.0066385578 | AN123: =AL123-$M$13/12-AM123 -> -0.082318099 | AO123: 38.09 | AP123: =(AO122-AO123)/AO123 -> 0.038592807 | AQ123: =AP123-$E$7/12 -> 0.035054473 | AR123: =E123*$N$17 -> -0.0041635874 | AS123: =AQ123-$N$13/12-AR123 -> 0.033998036 | AT123: =AT124*(1+AU123) -> 76.113214 | AU123: =$F$32*E123+$G$32*H123+$H$32*M123+$I$32*R123+$J$32*W123+$K$32*AB123+$L$32*AG123+$M$32*AL123+$N$32*AQ123 -> -0.014355506 | AV123: 53.78 | AW123: =(AV122-AV123)/AV123 -> -0.00204537 | AX123: =AW123-$E$7/12 -> -0.0055837034 | AZ123: =E123-AX123 -> -0.0034441085
B124: 43472 | C124: 54.98 | D124: =(C123-C124)/C124 -> -0.0060021826 | E124: =D124-$E$7/12 -> -0.0095405159 | F124: 93.34 | G124: =(F123-F124)/F124 -> -0.048532248 | H124: =G124-$E$7/12 -> -0.052070581 | I124: =$G$17*E124 -> -0.011080599 | J124: =H124-$G$13/12-I124 -> -0.054610822 | K124: 16.11 | L124: =(K123-K124)/K124 -> -0.066418374 | M124: =L124-$E$7/12 -> -0.069956707 | N124: =$H$17*E124 -> -0.017038286 | O124: =M124-$G$13/12-N124 -> -0.06653926 | P124: 262.62 | Q124: =(P123-P124)/P124 -> 0.069415886 | R124: =Q124-$E$7/12 -> 0.065877553 | S124: =E124*$I$17 -> -0.0070594429 | T124: =R124-$I$13/12-S124 -> 0.062543791 | U124: 322.99 | V124: =(U123-U124)/U124 -> -0.090529119 | W124: =V124-$E$7/12 -> -0.094067452 | X124: =E124*$J$17 -> -0.010958415 | Y124: =W124-$J$13/12-X124 -> -0.10380504 | Z124: 1886.61 | AA124: =(Z123-Z124)/Z124 -> 0.04229809 | AB124: =AA124-$E$7/12 -> 0.038759757 | AC124: =E124*$K$17 -> -0.0095884256 | AD124: =AB124-$K$13/12-AC124 -> 0.042222364 | AE124: 213.69 | AF124: =(AE123-AE124)/AE124 -> 0.066544995 | AG124: =AF124-$E$7/12 -> 0.063006662 | AH124: =E124*$L$17 -> -0.0081416952 | AI124: =AG124-$L$13/12-AH124 -> 0.067497002 | AJ124: 94.69 | AK124: =(AJ123-AJ124)/AJ124 -> 0.019748654 | AL124: =AK124-$E$7/12 -> 0.01621032 | AM124: =E124*$M$17 -> -0.0070155723 | AN124: =AL124-$M$13/12-AM124 -> 0.022107486 | AO124: 36.79 | AP124: =(AO123-AO124)/AO124 -> 0.035335689 | AQ124: =AP124-$E$7/12 -> 0.031797356 | AR124: =E124*$N$17 -> -0.0044000443 | AS124: =AQ124-$N$13/12-AR124 -> 0.030977376 | AT124: =AT125*(1+AU124) -> 77.221772 | AU124: =$F$32*E124+$G$32*H124+$H$32*M124+$I$32*R124+$J$32*W124+$K$32*AB124+$L$32*AG124+$M$32*AL124+$N$32*AQ124 -> 0.011224273 | AV124: 53.37 | AW124: =(AV123-AV124)/AV124 -> 0.0076822185 | AX124: =AW124-$E$7/12 -> 0.0041438851 | AZ124: =E124-AX124 -> -0.013684401
B125: 43471 | C125: 54.43 | D125: =(C124-C125)/C125 -> 0.010104722 | E125: =D125-$E$7/12 -> 0.0065663883 | F125: 94.68 | G125: =(F124-F125)/F125 -> -0.014152936 | H125: =G125-$E$7/12 -> -0.01769127 | I125: =$G$17*E125 -> 0.0076263711 | J125: =H125-$G$13/12-I125 -> -0.03893848 | K125: 14.9 | L125: =(K124-K125)/K125 -> 0.081208054 | M125: =L125-$E$7/12 -> 0.07766972 | N125: =$H$17*E125 -> 0.01172683 | O125: =M125-$G$13/12-N125 -> 0.052322051 | P125: 251.79 | Q125: =(P124-P125)/P125 -> 0.043012034 | R125: =Q125-$E$7/12 -> 0.039473701 | S125: =E125*$I$17 -> 0.0048587565 | T125: =R125-$I$13/12-S125 -> 0.024221739 | U125: 367.32 | V125: =(U124-U125)/U125 -> -0.12068496 | W125: =V125-$E$7/12 -> -0.12422329 | X125: =E125*$J$17 -> 0.0075422761 | Y125: =W125-$J$13/12-X125 -> -0.15246157 | Z125: 1874.71 | AA125: =(Z124-Z125)/Z125 -> 0.0063476484 | AB125: =AA125-$E$7/12 -> 0.0028093151 | AC125: =E125*$K$17 -> 0.0065993628 | AD125: =AB125-$K$13/12-AC125 -> -0.0099158662 | AE125: 207.97 | AF125: =(AE124-AE125)/AE125 -> 0.027503967 | AG125: =AF125-$E$7/12 -> 0.023965634 | AH125: =E125*$L$17 -> 0.0056036312 | AI125: =AG125-$L$13/12-AH125 -> 0.014710648 | AJ125: 83.83 | AK125: =(AJ124-AJ125)/AJ125 -> 0.12954789 | AL125: =AK125-$E$7/12 -> 0.12600956 | AM125: =E125*$M$17 -> 0.0048285619 | AN125: =AL125-$M$13/12-AM125 -> 0.12006259 | AO125: 36.83 | AP125: =(AO124-AO125)/AO125 -> -0.0010860711 | AQ125: =AP125-$E$7/12 -> -0.0046244045 | AR125: =E125*$N$17 -> 0.0030283896 | AS125: =AQ125-$N$13/12-AR125 -> -0.012872818 | AT125: =AT126*(1+AU125) -> 76.364634 | AU125: =$F$32*E125+$G$32*H125+$H$32*M125+$I$32*R125+$J$32*W125+$K$32*AB125+$L$32*AG125+$M$32*AL125+$N$32*AQ125 -> -0.00052984825 | AV125: 53.44 | AW125: =(AV124-AV125)/AV125 -> -0.0013098802 | AX125: =AW125-$E$7/12 -> -0.0048482136 | AZ125: =E125-AX125 -> 0.011414602
B126: 43470 | C126: 51.03 | D126: =(C125-C126)/C126 -> 0.066627474 | E126: =D126-$E$7/12 -> 0.063089141 | F126: 88.75 | G126: =(F125-F126)/F126 -> 0.066816901 | H126: =G126-$E$7/12 -> 0.063278568 | I126: =$G$17*E126 -> 0.07327334 | J126: =H126-$G$13/12-I126 -> -0.023615611 | K126: 12.34 | L126: =(K125-K126)/K126 -> 0.20745543 | M126: =L126-$E$7/12 -> 0.2039171 | N126: =$H$17*E126 -> 0.1126701 | O126: =M126-$G$13/12-N126 -> 0.077626161 | P126: 228.27 | Q126: =(P125-P126)/P126 -> 0.10303588 | R126: =Q126-$E$7/12 -> 0.099497545 | S126: =E126*$I$17 -> 0.046682401 | T126: =R126-$I$13/12-S126 -> 0.042421939 | U126: 343.28 | V126: =(U125-U126)/U126 -> 0.070030296 | W126: =V126-$E$7/12 -> 0.066491963 | X126: =E126*$J$17 -> 0.072465364 | Y126: =W126-$J$13/12-X126 -> -0.026669403 | Z126: 1656.22 | AA126: =(Z125-Z126)/Z126 -> 0.13192088 | AB126: =AA126-$E$7/12 -> 0.12838255 | AC126: =E126*$K$17 -> 0.063405955 | AD126: =AB126-$K$13/12-AC126 -> 0.058850773 | AE126: 189.85 | AF126: =(AE125-AE126)/AE126 -> 0.095443771 | AG126: =AF126-$E$7/12 -> 0.091905438 | AH126: =E126*$L$17 -> 0.053839075 | AI126: =AG126-$L$13/12-AH126 -> 0.034415008 | AJ126: 76.06 | AK126: =(AJ125-AJ126)/AJ126 -> 0.10215619 | AL126: =AK126-$E$7/12 -> 0.098617859 | AM126: =E126*$M$17 -> 0.046392295 | AN126: =AL126-$M$13/12-AM126 -> 0.051107158 | AO126: 33.81 | AP126: =(AO125-AO126)/AO126 -> 0.089322686 | AQ126: =AP126-$E$7/12 -> 0.085784352 | AR126: =E126*$N$17 -> 0.029096436 | AS126: =AQ126-$N$13/12-AR126 -> 0.051467892 | AT126: =AT127*(1+AU126) -> 76.405117 | AU126: =$F$32*E126+$G$32*H126+$H$32*M126+$I$32*R126+$J$32*W126+$K$32*AB126+$L$32*AG126+$M$32*AL126+$N$32*AQ126 -> 0.090534448 | AV126: 53.06 | AW126: =(AV125-AV126)/AV126 -> 0.0071617037 | AX126: =AW126-$E$7/12 -> 0.0036233704 | AZ126: =E126-AX126 -> 0.05946577
B127: 43469 | C127: 54.32 | D127: =(C126-C127)/C127 -> -0.06056701 | E127: =D127-$E$7/12 -> -0.064105344 | F127: 96.33 | G127: =(F126-F127)/F127 -> -0.078687844 | H127: =G127-$E$7/12 -> -0.082226177 | I127: =$G$17*E127 -> -0.074453584 | J127: =H127-$G$13/12-I127 -> -0.021393433 | K127: 15.91 | L127: =(K126-K127)/K127 -> -0.22438718 | M127: =L127-$E$7/12 -> -0.22792551 | N127: =$H$17*E127 -> -0.11448492 | O127: =M127-$G$13/12-N127 -> -0.12706143 | P127: 233.94 | Q127: =(P126-P127)/P127 -> -0.024236984 | R127: =Q127-$E$7/12 -> -0.027775317 | S127: =E127*$I$17 -> -0.047434334 | T127: =R127-$I$13/12-S127 -> 0.0092658113 | U127: 370.54 | V127: =(U126-U127)/U127 -> -0.073568306 | W127: =V127-$E$7/12 -> -0.077106639 | X127: =E127*$J$17 -> -0.073632594 | Y127: =W127-$J$13/12-X127 -> -0.024170047 | Z127: 1854.99 | AA127: =(Z126-Z127)/Z127 -> -0.10715422 | AB127: =AA127-$E$7/12 -> -0.11069255 | AC127: =E127*$K$17 -> -0.064427261 | AD127: =AB127-$K$13/12-AC127 -> -0.052391107 | AE127: 203.7 | AF127: =(AE126-AE127)/AE127 -> -0.067992145 | AG127: =AF127-$E$7/12 -> -0.071530479 | AH127: =E127*$L$17 -> -0.054706284 | AI127: =AG127-$L$13/12-AH127 -> -0.02047555 | AJ127: 77.68 | AK127: =(AJ126-AJ127)/AJ127 -> -0.020854789 | AL127: =AK127-$E$7/12 -> -0.024393122 | AM127: =E127*$M$17 -> -0.047139555 | AN127: =AL127-$M$13/12-AM127 -> 0.021628026 | AO127: 34.28 | AP127: =(AO126-AO127)/AO127 -> -0.013710618 | AQ127: =AP127-$E$7/12 -> -0.017248952 | AR127: =E127*$N$17 -> -0.029565105 | AS127: =AQ127-$N$13/12-AR127 -> 0.0070961285 | AT127: =AT128*(1+AU127) -> 70.062085 | AU127: =$F$32*E127+$G$32*H127+$H$32*M127+$I$32*R127+$J$32*W127+$K$32*AB127+$L$32*AG127+$M$32*AL127+$N$32*AQ127 -> -0.064995644 | AV127: 52.82 | AW127: =(AV126-AV127)/AV127 -> 0.0045437334 | AX127: =AW127-$E$7/12 -> 0.0010054001 | AZ127: =E127-AX127 -> -0.065110744
B128: 43468 | C128: 51.08 | D128: =(C127-C128)/C128 -> 0.063429914 | E128: =D128-$E$7/12 -> 0.059891581 | F128: 89.04 | G128: =(F127-F128)/F128 -> 0.081873315 | H128: =G128-$E$7/12 -> 0.078334982 | I128: =$G$17*E128 -> 0.069559611 | J128: =H128-$G$13/12-I128 -> -0.0048454689 | K128: 18.66 | L128: =(K127-K128)/K128 -> -0.14737406 | M128: =L128-$E$7/12 -> -0.1509124 | N128: =$H$17*E128 -> 0.10695961 | O128: =M128-$G$13/12-N128 -> -0.27149285 | P128: 230.71 | Q128: =(P127-P128)/P128 -> 0.01400026 | R128: =Q128-$E$7/12 -> 0.010461927 | S128: =E128*$I$17 -> 0.044316387 | T128: =R128-$I$13/12-S128 -> -0.044247665 | U128: 356.56 | V128: =(U127-U128)/U128 -> 0.039207987 | W128: =V128-$E$7/12 -> 0.035669654 | X128: =E128*$J$17 -> 0.068792587 | Y128: =W128-$J$13/12-X128 -> -0.053818934 | Z128: 1744.91 | AA128: =(Z127-Z128)/Z128 -> 0.063086348 | AB128: =AA128-$E$7/12 -> 0.059548015 | AC128: =E128*$K$17 -> 0.060192338 | AD128: =AB128-$K$13/12-AC128 -> -0.0067701416 | AE128: 191.89 | AF128: =(AE127-AE128)/AE128 -> 0.061545677 | AG128: =AF128-$E$7/12 -> 0.058007344 | AH128: =E128*$L$17 -> 0.051110338 | AI128: =AG128-$L$13/12-AH128 -> 0.003245651 | AJ128: 74.34 | AK128: =(AJ127-AJ128)/AJ128 -> 0.044928706 | AL128: =AK128-$E$7/12 -> 0.041390373 | AM128: =E128*$M$17 -> 0.044040984 | AN128: =AL128-$M$13/12-AM128 -> -0.003769018 | AO128: 32.51 | AP128: =(AO127-AO128)/AO128 -> 0.054444786 | AQ128: =AP128-$E$7/12 -> 0.050906453 | AR128: =E128*$N$17 -> 0.027621736 | AS128: =AQ128-$N$13/12-AR128 -> 0.018064693 | AT128: =AT129*(1+AU128) -> 74.932362 | AU128: =$F$32*E128+$G$32*H128+$H$32*M128+$I$32*R128+$J$32*W128+$K$32*AB128+$L$32*AG128+$M$32*AL128+$N$32*AQ128 -> 0.044814235 | AV128: 52.82 | AW128: =(AV127-AV128)/AV128 -> 0 | AX128: =AW128-$E$7/12 -> -0.0035383333 | AZ128: =E128-AX128 -> 0.063429914
B129: 43467 | C129: 50 | D129: =(C128-C129)/C129 -> 0.0216 | E129: =D129-$E$7/12 -> 0.018061667 | F129: 81.99 | G129: =(F128-F129)/F129 -> 0.085986096 | H129: =G129-$E$7/12 -> 0.082447763 | I129: =$G$17*E129 -> 0.020977281 | J129: =H129-$G$13/12-I129 -> 0.047849642 | K129: 21.33 | L129: =(K128-K129)/K129 -> -0.12517581 | M129: =L129-$E$7/12 -> -0.12871414 | N129: =$H$17*E129 -> 0.032256101 | O129: =M129-$G$13/12-N129 -> -0.17459108 | P129: 208.42 | Q129: =(P128-P129)/P129 -> 0.10694751 | R129: =Q129-$E$7/12 -> 0.10340918 | S129: =E129*$I$17 -> 0.013364613 | T129: =R129-$I$13/12-S129 -> 0.079651358 | U129: 358.1 | V129: =(U128-U129)/U129 -> -0.0043004747 | W129: =V129-$E$7/12 -> -0.0078388081 | X129: =E129*$J$17 -> 0.020745967 | Y129: =W129-$J$13/12-X129 -> -0.049280777 | Z129: 1697.04 | AA129: =(Z128-Z129)/Z129 -> 0.028207939 | AB129: =AA129-$E$7/12 -> 0.024669605 | AC129: =E129*$K$17 -> 0.018152367 | AD129: =AB129-$K$13/12-AC129 -> 0.00039141977 | AE129: 185.14 | AF129: =(AE128-AE129)/AE129 -> 0.036458896 | AG129: =AF129-$E$7/12 -> 0.032920563 | AH129: =E129*$L$17 -> 0.015413484 | AI129: =AG129-$L$13/12-AH129 -> 0.013855724 | AJ129: 70.26 | AK129: =(AJ128-AJ129)/AJ129 -> 0.058070026 | AL129: =AK129-$E$7/12 -> 0.054531692 | AM129: =E129*$M$17 -> 0.013281559 | AN129: =AL129-$M$13/12-AM129 -> 0.040131727 | AO129: 33 | AP129: =(AO128-AO129)/AO129 -> -0.014848485 | AQ129: =AP129-$E$7/12 -> -0.018386818 | AR129: =E129*$N$17 -> 0.0083299618 | AS129: =AQ129-$N$13/12-AR129 -> -0.031936804 | AT129: =AT130*(1+AU129) -> 71.718359 | AU129: =$F$32*E129+$G$32*H129+$H$32*M129+$I$32*R129+$J$32*W129+$K$32*AB129+$L$32*AG129+$M$32*AL129+$N$32*AQ129 -> 0.043902834 | AV129: 52.37 | AW129: =(AV128-AV129)/AV129 -> 0.0085927057 | AX129: =AW129-$E$7/12 -> 0.0050543724 | AZ129: =E129-AX129 -> 0.013007294
B130: 43466 | C130: 49.29 | D130: =(C129-C130)/C130 -> 0.014404545 | E130: =D130-$E$7/12 -> 0.010866211 | F130: 85.94 | G130: =(F129-F130)/F130 -> -0.045962299 | H130: =G130-$E$7/12 -> -0.049500633 | I130: =$G$17*E130 -> 0.012620295 | J130: =H130-$G$13/12-I130 -> -0.075741767 | K130: 20.47 | L130: =(K129-K130)/K130 -> 0.042012702 | M130: =L130-$E$7/12 -> 0.038474368 | N130: =$H$17*E130 -> 0.019405829 | O130: =M130-$G$13/12-N130 -> 0.0054477 | P130: 204.5 | Q130: =(P129-P130)/P130 -> 0.019168704 | R130: =Q130-$E$7/12 -> 0.015630371 | S130: =E130*$I$17 -> 0.0080403826 | T130: =R130-$I$13/12-S130 -> -0.0028032169 | U130: 339.5 | V130: =(U129-U130)/U130 -> 0.054786451 | W130: =V130-$E$7/12 -> 0.051248117 | X130: =E130*$J$17 -> 0.012481133 | Y130: =W130-$J$13/12-X130 -> 0.018070983 | Z130: 1832.81 | AA130: =(Z129-Z130)/Z130 -> -0.074077509 | AB130: =AA130-$E$7/12 -> -0.077615843 | AC130: =E130*$K$17 -> 0.010920778 | AD130: =AB130-$K$13/12-AC130 -> -0.094662439 | AE130: 183.53 | AF130: =(AE129-AE130)/AE130 -> 0.0087724078 | AG130: =AF130-$E$7/12 -> 0.0052340744 | AH130: =E130*$L$17 -> 0.0092730184 | AI130: =AG130-$L$13/12-AH130 -> -0.0076902988 | AJ130: 68.14 | AK130: =(AJ129-AJ130)/AJ130 -> 0.031112416 | AL130: =AK130-$E$7/12 -> 0.027574082 | AM130: =E130*$M$17 -> 0.0079904159 | AN130: =AL130-$M$13/12-AM130 -> 0.01846526 | AO130: 31.94 | AP130: =(AO129-AO130)/AO130 -> 0.033187226 | AQ130: =AP130-$E$7/12 -> 0.029648893 | AR130: =E130*$N$17 -> 0.0050114492 | AS130: =AQ130-$N$13/12-AR130 -> 0.019417419 | AT130: =AT131*(1+AU130) -> 68.70214 | AU130: =$F$32*E130+$G$32*H130+$H$32*M130+$I$32*R130+$J$32*W130+$K$32*AB130+$L$32*AG130+$M$32*AL130+$N$32*AQ130 -> -0.0057586792 | AV130: 52.29 | AW130: =(AV129-AV130)/AV130 -> 0.0015299292 | AX130: =AW130-$E$7/12 -> -0.0020084041 | AZ130: =E130-AX130 -> 0.012874615
B131: 43112 | C131: 45.22 | D131: =(C130-C131)/C131 -> 0.090004423 | E131: =D131-$E$7/12 -> 0.086466089 | F131: 75.1 | G131: =(F130-F131)/F131 -> 0.14434088 | H131: =G131-$E$7/12 -> 0.14080255 | I131: =$G$17*E131 -> 0.10042392 | J131: =H131-$G$13/12-I131 -> 0.026757781 | K131: 22.19 | L131: =(K130-K131)/K131 -> -0.077512393 | M131: =L131-$E$7/12 -> -0.081050726 | N131: =$H$17*E131 -> 0.15441869 | O131: =M131-$G$13/12-N131 -> -0.24909026 | P131: 194.1 | Q131: =(P130-P131)/P131 -> 0.053580629 | R131: =Q131-$E$7/12 -> 0.050042295 | S131: =E131*$I$17 -> 0.063980023 | T131: =R131-$I$13/12-S131 -> -0.024330933 | U131: 267.66 | V131: =(U130-U131)/U131 -> 0.26840021 | W131: =V131-$E$7/12 -> 0.26486188 | X131: =E131*$J$17 -> 0.099316563 | Y131: =W131-$J$13/12-X131 -> 0.14484931 | Z131: 1722.42 | AA131: =(Z130-Z131)/Z131 -> 0.064090059 | AB131: =AA131-$E$7/12 -> 0.060551726 | AC131: =E131*$K$17 -> 0.086900296 | AD131: =AB131-$K$13/12-AC131 -> -0.032474389 | AE131: 171.82 | AF131: =(AE130-AE131)/AE131 -> 0.068152718 | AG131: =AF131-$E$7/12 -> 0.064614385 | AH131: =E131*$L$17 -> 0.07378852 | AI131: =AG131-$L$13/12-AH131 -> -0.01282549 | AJ131: 64.4 | AK131: =(AJ130-AJ131)/AJ131 -> 0.058074534 | AL131: =AK131-$E$7/12 -> 0.054536201 | AM131: =E131*$M$17 -> 0.063582421 | AN131: =AL131-$M$13/12-AM131 -> -0.010164627 | AO131: 31.05 | AP131: =(AO130-AO131)/AO131 -> 0.028663446 | AQ131: =AP131-$E$7/12 -> 0.025125113 | AR131: =E131*$N$17 -> 0.039877783 | AS131: =AQ131-$N$13/12-AR131 -> -0.019972695 | AT131: =AT132*(1+AU131) -> 69.100065 | AU131: =$F$32*E131+$G$32*H131+$H$32*M131+$I$32*R131+$J$32*W131+$K$32*AB131+$L$32*AG131+$M$32*AL131+$N$32*AQ131 -> 0.089711704 | AV131: 51.64 | AW131: =(AV130-AV131)/AV131 -> 0.012587142 | AX131: =AW131-$E$7/12 -> 0.0090488084 | AZ131: =E131-AX131 -> 0.077417281
B132: 43111 | C132: 49.85 | D132: =(C131-C132)/C132 -> -0.092878636 | E132: =D132-$E$7/12 -> -0.096416969 | F132: 84.51 | G132: =(F131-F132)/F132 -> -0.11134777 | H132: =G132-$E$7/12 -> -0.1148861 | I132: =$G$17*E132 -> -0.11198113 | J132: =H132-$G$13/12-I132 -> -0.016525811 | K132: 23.37 | L132: =(K131-K132)/K132 -> -0.050492084 | M132: =L132-$E$7/12 -> -0.054030417 | N132: =$H$17*E132 -> -0.17218984 | O132: =M132-$G$13/12-N132 -> 0.10453858 | P132: 220.37 | Q132: =(P131-P132)/P132 -> -0.1192086 | R132: =Q132-$E$7/12 -> -0.12274694 | S132: =E132*$I$17 -> -0.071343112 | T132: =R132-$I$13/12-S132 -> -0.061797031 | U132: 286.13 | V132: =(U131-U132)/U132 -> -0.064551078 | W132: =V132-$E$7/12 -> -0.068089412 | X132: =E132*$J$17 -> -0.11074633 | Y132: =W132-$J$13/12-X132 -> 0.021960917 | Z132: 1891.88 | AA132: =(Z131-Z132)/Z132 -> -0.089572277 | AB132: =AA132-$E$7/12 -> -0.093110611 | AC132: =E132*$K$17 -> -0.096901146 | AD132: =AB132-$K$13/12-AC132 -> -0.0023352828 | AE132: 180.32 | AF132: =(AE131-AE132)/AE132 -> -0.047138421 | AG132: =AF132-$E$7/12 -> -0.050676754 | AH132: =E132*$L$17 -> -0.082280412 | AI132: =AG132-$L$13/12-AH132 -> 0.027952303 | AJ132: 66.72 | AK132: =(AJ131-AJ132)/AJ132 -> -0.034772182 | AL132: =AK132-$E$7/12 -> -0.038310516 | AM132: =E132*$M$17 -> -0.070899752 | AN132: =AL132-$M$13/12-AM132 -> 0.03147083 | AO132: 32.55 | AP132: =(AO131-AO132)/AO132 -> -0.046082949 | AQ132: =AP132-$E$7/12 -> -0.049621283 | AR132: =E132*$N$17 -> -0.044467085 | AS132: =AQ132-$N$13/12-AR132 -> -0.010374222 | AT132: =AT133*(1+AU132) -> 63.411327 | AU132: =$F$32*E132+$G$32*H132+$H$32*M132+$I$32*R132+$J$32*W132+$K$32*AB132+$L$32*AG132+$M$32*AL132+$N$32*AQ132 -> -0.086908458 | AV132: 51.51 | AW132: =(AV131-AV132)/AV132 -> 0.0025237818 | AX132: =AW132-$E$7/12 -> -0.0010145515 | AZ132: =E132-AX132 -> -0.095402418
... B175: 42008 | C175: 35.67 | D175: =(C174-C175)/C175 -> 0.01065321 | E175: =D175-$E$7/12 -> 0.0071148766 | F175: 21.09 | G175: =(F174-F175)/F175 -> 0.01754386 | H175: =G175-$E$7/12 -> 0.014005526 | I175: =$G$17*E175 -> 0.0082633995 | J175: =H175-$G$13/12-I175 -> -0.0078787126 | K175: 15.07 | L175: =(K174-K175)/K175 -> 0.10948905 | M175: =L175-$E$7/12 -> 0.10595072 | N175: =$H$17*E175 -> 0.012706368 | O175: =M175-$G$13/12-N175 -> 0.07962351 | P175: 131 | Q175: =(P174-P175)/P175 -> -0.0032061069 | R175: =Q175-$E$7/12 -> -0.0067444402 | S175: =E175*$I$17 -> 0.0052646069 | T175: =R175-$I$13/12-S175 -> -0.022402252 | U175: 79.5 | V175: =(U174-U175)/U175 -> 0.12138365 | W175: =V175-$E$7/12 -> 0.11784531 | X175: =E175*$J$17 -> 0.00817228 | Y175: =W175-$J$13/12-X175 -> 0.088977033 | Z175: 1237.81 | AA175: =(Z174-Z175)/Z175 -> -0.053134164 | AB175: =AA175-$E$7/12 -> -0.056672498 | AC175: =E175*$K$17 -> 0.0071506054 | AD175: =AB175-$K$13/12-AC175 -> -0.069948922 | AE175: 106.98 | AF175: =(AE174-AE175)/AE175 -> 0.041503085 | AG175: =AF175-$E$7/12 -> 0.037964751 | AH175: =E175*$L$17 -> 0.0060717007 | AI175: =AG175-$L$13/12-AH175 -> 0.028241696 | AJ175: 49.58 | AK175: =(AJ174-AJ175)/AJ175 -> 0.048003227 | AL175: =AK175-$E$7/12 -> 0.044464894 | AM175: =E175*$M$17 -> 0.0052318901 | AN175: =AL175-$M$13/12-AM175 -> 0.038114597 | AO175: 26.02 | AP175: =(AO174-AO175)/AO175 -> -0.048424289 | AQ175: =AP175-$E$7/12 -> -0.051962622 | AR175: =E175*$N$17 -> 0.0032813501 | AS175: =AQ175-$N$13/12-AR175 -> -0.060463997 | AT175: =AT176*(1+AU175) -> 36.378756 | AU175: =$F$32*E175+$G$32*H175+$H$32*M175+$I$32*R175+$J$32*W175+$K$32*AB175+$L$32*AG175+$M$32*AL175+$N$32*AQ175 -> 0.0091194587 | AV175: 52.77 | AW175: =(AV174-AV175)/AV175 -> -0.00018950161 | AX175: =AW175-$E$7/12 -> -0.0037278349 | AZ175: =E175-AX175 -> 0.010842712
B176: 42007 | C176: 36.05 | D176: =(C175-C176)/C176 -> -0.010540915 | E176: =D176-$E$7/12 -> -0.014079249 | F176: 18.6 | G176: =(F175-F176)/F176 -> 0.13387097 | H176: =G176-$E$7/12 -> 0.13033263 | I176: =$G$17*E176 -> -0.016351999 | J176: =H176-$G$13/12-I176 -> 0.13306379 | K176: 12.58 | L176: =(K175-K176)/K176 -> 0.19793323 | M176: =L176-$E$7/12 -> 0.19439489 | N176: =$H$17*E176 -> -0.025143952 | O176: =M176-$G$13/12-N176 -> 0.20591801 | P176: 138.74 | Q176: =(P175-P176)/P176 -> -0.055787805 | R176: =Q176-$E$7/12 -> -0.059326138 | S176: =E176*$I$17 -> -0.010417849 | T176: =R176-$I$13/12-S176 -> -0.059301494 | U176: 59.53 | V176: =(U175-U176)/U176 -> 0.33546111 | W176: =V176-$E$7/12 -> 0.33192278 | X176: =E176*$J$17 -> -0.016171688 | Y176: =W176-$J$13/12-X176 -> 0.32739847 | Z176: 1164.15 | AA176: =(Z175-Z176)/Z176 -> 0.063273633 | AB176: =AA176-$E$7/12 -> 0.0597353 | AC176: =E176*$K$17 -> -0.01414995 | AD176: =AB176-$K$13/12-AC176 -> 0.067759432 | AE176: 113.61 | AF176: =(AE175-AE176)/AE176 -> -0.058357539 | AG176: =AF176-$E$7/12 -> -0.061895872 | AH176: =E176*$L$17 -> -0.012014964 | AI176: =AG176-$L$13/12-AH176 -> -0.053532264 | AJ176: 47.35 | AK176: =(AJ175-AJ176)/AJ176 -> 0.047096093 | AL176: =AK176-$E$7/12 -> 0.04355776 | AM176: =E176*$M$17 -> -0.010353107 | AN176: =AL176-$M$13/12-AM176 -> 0.052792461 | AO176: 27.42 | AP176: =(AO175-AO176)/AO176 -> -0.051057622 | AQ176: =AP176-$E$7/12 -> -0.054595956 | AR176: =E176*$N$17 -> -0.0064932881 | AS176: =AQ176-$N$13/12-AR176 -> -0.053322692 | AT176: =C176 -> 36.05 | AU176: =$F$32*E176+$G$32*H176+$H$32*M176+$I$32*R176+$J$32*W176+$K$32*AB176+$L$32*AG176+$M$32*AL176+$N$32*AQ176 -> 0.044229395 | AV176: 52.76 | AW176: =(AV175-AV176)/AV176 -> 0.00018953753 | AX176: =AW176-$E$7/12 -> -0.0033487958 | AZ176: =E176-AX176 -> -0.010730453
F177: SUMMARY OUTPUT | K177: SUMMARY OUTPUT | P177: SUMMARY OUTPUT | U177: SUMMARY OUTPUT | Z177: SUMMARY OUTPUT | AE177: SUMMARY OUTPUT | AJ177: SUMMARY OUTPUT | AO177: SUMMARY OUTPUT | AZ177: =AVERAGE(AZ57:AZ176)*12 -> 0.10792455 | BA177: Tracking Error
AZ178: =_xlfn.STDEV.S(AZ57:AZ176) -> 0.050701921 | BA178: SD of TE
F179: Regression Statistics | K179: Regression Statistics | P179: Regression Statistics | U179: Regression Statistics | Z179: Regression Statistics | AE179: Regression Statistics | AJ179: Regression Statistics | AO179: Regression Statistics | AZ179: =CORREL(AU57:AU176,E57:E176) -> 0.909702 | BA179: Correlation
F180: Multiple R | G180: 0.70670402 | K180: Multiple R | L180: 0.53535365 | P180: Multiple R | Q180: 0.66689625 | U180: Multiple R | V180: 0.52929469 | Z180: Multiple R | AA180: 0.6449062 | AE180: Multiple R | AF180: 0.73116831 | AJ180: Multiple R | AK180: 0.5585189 | AO180: Multiple R | AP180: 0.45693716 | AZ180: =RSQ(AU57:AU176,E57:E176) -> 0.82755774 | BA180: R^2
F181: R Square | G181: 0.49943058 | K181: R Square | L181: 0.28660353 | P181: R Square | Q181: 0.4447506 | U181: R Square | V181: 0.28015287 | Z181: R Square | AA181: 0.41590401 | AE181: R Square | AF181: 0.5346071 | AJ181: R Square | AK181: 0.31194336 | AO181: R Square | AP181: 0.20879157 | AZ181: =SLOPE(AU57:AU176,E57:E176) -> 0.91056787 | BA181: Slope (B)
F182: Adjusted R Square | G182: 0.49518846 | K182: Adjusted R Square | L182: 0.28055779 | P182: Adjusted R Square | Q182: 0.4400451 | U182: Adjusted R Square | V182: 0.27405247 | Z182: Adjusted R Square | AA182: 0.41095404 | AE182: Adjusted R Square | AF182: 0.5306631 | AJ182: Adjusted R Square | AK182: 0.30611237 | AO182: Adjusted R Square | AP182: 0.20208641
F183: Standard Error | G183: 0.063777322 | K183: Standard Error | L183: 0.15454647 | P183: Standard Error | Q183: 0.045348681 | U183: Standard Error | V183: 0.1009901 | Z183: Standard Error | AA183: 0.065328293 | AE183: Standard Error | AF183: 0.043673279 | AJ183: Standard Error | AK183: 0.059902615 | AO183: Standard Error | AP183: 0.049244131
F184: Observations | G184: 120 | K184: Observations | L184: 120 | P184: Observations | Q184: 120 | U184: Observations | V184: 120 | Z184: Observations | AA184: 120 | AE184: Observations | AF184: 120 | AJ184: Observations | AK184: 120 | AO184: Observations | AP184: 120
F186: ANOVA | K186: ANOVA | P186: ANOVA | U186: ANOVA | Z186: ANOVA | AE186: ANOVA | AJ186: ANOVA | AO186: ANOVA
G187: df | H187: SS | I187: MS | J187: F | L187: df | M187: SS | N187: MS | O187: F | Q187: df | R187: SS | S187: MS | T187: F | V187: df | W187: SS | X187: MS | Y187: F | AA187: df | AB187: SS | AC187: MS | AD187: F | AF187: df | AG187: SS | AH187: MS | AI187: F | AK187: df | AL187: SS | AM187: MS | AN187: F | AP187: df | AQ187: SS | AR187: MS | AS187: F
F188: Regression | G188: 1 | H188: 0.47887855 | I188: 0.47887855 | J188: 117.73154 | K188: Regression | L188: 1 | M188: 1.1322719 | N188: 1.1322719 | O188: 47.40592 | P188: Regression | Q188: 1 | R188: 0.19437472 | S188: 0.19437472 | T188: 94.517115 | U188: Regression | V188: 1 | W188: 0.46837571 | X188: 0.46837571 | Y188: 45.923692 | Z188: Regression | AA188: 1 | AB188: 0.35858615 | AC188: 0.35858615 | AD188: 84.021589 | AE188: Regression | AF188: 1 | AG188: 0.2585405 | AH188: 0.2585405 | AI188: 135.54921 | AJ188: Regression | AK188: 1 | AL188: 0.19196635 | AM188: 0.19196635 | AN188: 53.497509 | AO188: Regression | AP188: 1 | AQ188: 0.075511485 | AR188: 0.075511485 | AS188: 31.138956
F189: Residual | G189: 118 | H189: 0.47997053 | I189: 0.0040675468 | K189: Residual | L189: 118 | M189: 2.818384 | N189: 0.02388461 | P189: Residual | Q189: 118 | R189: 0.24266734 | S189: 0.0020565029 | U189: Residual | V189: 118 | W189: 1.2034819 | X189: 0.010198999 | Z189: Residual | AA189: 118 | AB189: 0.50359873 | AC189: 0.0042677859 | AE189: Residual | AF189: 118 | AG189: 0.22506793 | AH189: 0.0019073553 | AJ189: Residual | AK189: 118 | AL189: 0.42342214 | AM189: 0.0035883232 | AO189: Residual | AP189: 118 | AQ189: 0.28614817 | AR189: 0.0024249845
F190: Total | G190: 119 | H190: 0.95884907 | K190: Total | L190: 119 | M190: 3.9506559 | P190: Total | Q190: 119 | R190: 0.43704206 | U190: Total | V190: 119 | W190: 1.6718576 | Z190: Total | AA190: 119 | AB190: 0.86218488 | AE190: Total | AF190: 119 | AG190: 0.48360843 | AJ190: Total | AK190: 119 | AL190: 0.6153885 | AO190: Total | AP190: 119 | AQ190: 0.36165965
G192: Coefficients | H192: Standard Error | I192: t Stat | J192: P-value | L192: Coefficients | M192: Standard Error | N192: t Stat | O192: P-value | Q192: Coefficients | R192: Standard Error | S192: t Stat | T192: P-value | V192: Coefficients | W192: Standard Error | X192: t Stat | Y192: P-value | AA192: Coefficients | AB192: Standard Error | AC192: t Stat | AD192: P-value | AF192: Coefficients | AG192: Standard Error | AH192: t Stat | AI192: P-value | AK192: Coefficients | AL192: Standard Error | AM192: t Stat | AN192: P-value | AP192: Coefficients | AQ192: Standard Error | AR192: t Stat | AS192: P-value
F193: Intercept | G193: 0.013620839 | H193: 0.0058509491 | I193: 2.3279709 | J193: 0.021616878 | K193: Intercept | L193: 0.027209673 | M193: 0.014178135 | N193: 1.9191292 | O193: 0.057383013 | P193: Intercept | Q193: 0.010393205 | R193: 0.0041603005 | S193: 2.4981862 | T193: 0.013859995 | U193: Intercept | V193: 0.020696001 | W193: 0.0092648592 | X193: 2.2338172 | Y193: 0.027379454 | Z193: Intercept | AA193: 0.0061258185 | AB193: 0.0059932356 | AC193: 1.0221221 | AD193: 0.30881406 | AE193: Intercept | AF193: 0.0036513549 | AG193: 0.0040065987 | AH193: 0.91133531 | AI193: 0.36397672 | AJ193: Intercept | AK193: 0.0011184064 | AL193: 0.0054954824 | AM193: 0.20351378 | AN193: 0.83908402 | AO193: Intercept | AP193: 0.0052200244 | AQ193: 0.0045176702 | AR193: 1.1554682 | AS193: 0.25023305
F194: X Variable 1 | G194: 1.1614255 | H194: 0.10703972 | I194: 10.850416 | J194: 1.9084476e-19 | K194: X Variable 1 | L194: 1.7858873 | M194: 0.25938076 | N194: 6.8851957 | O194: 2.9810855e-10 | P194: X Variable 1 | Q194: 0.73994352 | R194: 0.076110284 | S194: 9.7219913 | T194: 9.1497646e-17 | U194: X Variable 1 | V194: 1.1486187 | W194: 0.16949522 | X194: 6.7767022 | Y194: 5.1251088e-10 | Z194: X Variable 1 | AA194: 1.0050217 | AB194: 0.10964277 | AC194: 9.1663291 | AD194: 1.8758894e-15 | AE194: X Variable 1 | AF194: 0.85338102 | AG194: 0.073298399 | AH194: 11.64256 | AI194: 2.5080167e-21 | AJ194: X Variable 1 | AK194: 0.73534517 | AL194: 0.10053666 | AM194: 7.3141991 | AN194: 3.3901365e-11 | AO194: X Variable 1 | AP194: 0.46119564 | AQ194: 0.082648155 | AR194: 5.580229 | AS194: 1.5545353e-07
I198: p<0.1
I199: t>1.69

Sheet Data. Bond Duration & Convexity
B2: Calculate the approximate price change for a IGSB using only its D* and using D* and Convexity
B4: IGSB has the following characteristics:
B5: Maturity | C5: 13
B6: Coupon ($100 par) | C6: 0.0424
B7: Yield to maturity | C7: 0.0526
B8: Coupon (frequency) | C8: Semiannual
B9: Convexity (C) | C9: 1.21
B10: Current Bond Price | C10: =PV(C7/2,C5*2,-C6/2*100,-100) -> 90.482109 | D10: =_xlfn.FORMULATEXT(C10) -> =PV(C7/2,C5*2,-C6/2*100,-100)
B11: Modified Duration (D*) | C11: 2.6
B13: Changes in YTM | C13: YTM down 100bps
B14: with D* only | C14: =-C11*-1% -> 0.026 | D14: =_xlfn.FORMULATEXT(C14) -> =-C11*-1%
B15: Bond Price change | C15: =C10*(1+C14) -> 92.834644 | D15: =_xlfn.FORMULATEXT(C15) -> =C10*(1+C14)
B16: with D* and Convexity | C16: =C14+1/2*C9*-1%^2 -> 0.0260605 | D16: =_xlfn.FORMULATEXT(C16) -> =C14+1/2*C9*-1%^2
B17: Bond Price change | C17: =C10*(1+C16) -> 92.840118 | D17: =_xlfn.FORMULATEXT(C17) -> =C10*(1+C16)
